[
  "{\n  \"municipio\": \"ARAPIRACA\",\n  \"id\": \"arapiraca\",\n  \"cabecalho\": \"Alagoas , 28 de Setembro de 2020   •   Diário Oficial dos Municípios do Estado de Alagoas   •    ANO VIII | Nº 1382 \",\n  \"texto\": \"Alagoas , 28 de Setembro de 2020   •   Diário Oficial dos Municípios do Estado de Alagoas   •    ANO VIII | Nº 1382 \\n\\nESTADO DE ALAGOAS\\n\\nPREFEITURA MUNICIPAL DE ARAPIRACA\\n\\n\\n\\nPREFEITURA MUNICIPAL DE ARAPIRACA\\n\\nATA DA 1ª REUNIÃO EXTRAORDINÁRIA DO CONSELHO\\n\\nMUNICIPAL DE PREVIDÊNCIA DO INSTITUTO\\n\\nMUNICIPAL DE PREVIDÊNCIA DOS SERVIDORES\\n\\nPÚBLICOS DE ARAPIRACA\\n\\n\\n\\nINSTITUTO MUNICIPAL DE PREVIDÊNCIA\\n\\nCONSELHO MUNICIPAL DE PREVIDÊNCIA\\n\\n\\nATA DA 1ª REUNIÃO EXTRAORDINÁRIA DO CONSELHO\\n\\nMUNICIPAL DE PREVIDÊNCIA DO INSTITUTO\\n\\nMUNICIPAL DE PREVIDÊNCIA DOS SERVIDORES\\n\\nPÚBLICOS DE ARAPIRACA\\n\\n\\nAos 25 (vinte e cinco) dias do mês de setembro do ano de 2020 na\\n\\nsala de reuniões do Instituto Municipal de Previdência Social –\\n\\nIMPREV, localizado na Rua Padre Jefferson de Carvalho, nº 191,\\n\\nAlto do Cruzeiro, Arapiraca-Alagoas presentes estavam o Senhor\\n\\nRicardo Alexandre Vieira Leite, Presidente deste Conselho, e os\\n\\ndemais membros Méry Dayana dos Santos – Representante do\\n\\nPoder Executivo, Klebson Clementino da Silva – Representante\\n\\ndo Poder Executivo, Gedilza Barbosa Vital – Representante dos\\n\\nServidores Ativos da Câmara Municipal de Vereadores, Lucielle\\n\\nKarla Cunha Cajueiro – Representante dos Pensionistas.\\nA Reunião teve como pauta: A Deliberação sobre o projeto da Lei\\n\\nComplementar que dispõe sobre o plano de custeio do Regime Próprio\\n\\nde Previdência dos Servidores do Município de Arapiraca/AL.\\n\\nAo iniciar a reunião, o presidente entregou copia da referida Lei aos\\n\\nMembros do Conselho. Logo após foi iniciada a leitura integral do\\n\\nreferido projeto.\\n\\n\\n\\nAo término da leitura, o projeto de lei foi colocado para deliberação,\\n\\nsendo aprovado por unanimidade.\\n\\nDada a palavra aos membros do Conselho Municipal de Previdência\\n\\nnada mais foi acrescentado.\\n\\nDá-se por encerrada a reunião, a presente ata vai assinada por\\n\\nmim, Secretário-Executivo, Klebson Clementino da Silva, pelo\\n\\npresidente do Conselho, e demais membros presentes.\\n\\n\\nGEDILZA BARBOSA VITAL\\nRepresentante dos Servidores Ativos da Câmara\\n\\n\\n\\n\\n\\n\\n\\n\\nwww.diariomunicipal.com.br/ama                                                                                        2\\n\\n\\n\\nMÉRY DAYANA DOS SANTOS\\nRepresentante do Poder Executivo\\n\\n\\n\\nKLEBSON CLEMENTINO DA SILVA\\nRepresentante do Poder Executivo\\n\\n\\n\\nLUCIELLE KARLA CUNHA CAJUEIRO\\nRepresentante dos Pensionistas\\n\\n\\n\\nRICARDO ALEXANDRE VIEIRA LEITE\\nPresidente do Conselho Municipal de Previdência.\\n\\nPublicado por:\\nGean Fábio Carvalho de Oliveira\\n\\nCódigo Identificador:FB6384D4\",\n  \"data_publicacao\": \"2020-09-28\"\n}",
  "{\n  \"municipio\": \"ATALAIA\",\n  \"id\": \"atalaia\",\n  \"cabecalho\": \"Alagoas , 28 de Setembro de 2020   •   Diário Oficial dos Municípios do Estado de Alagoas   •    ANO VIII | Nº 1382 \",\n  \"texto\": \"Alagoas , 28 de Setembro de 2020   •   Diário Oficial dos Municípios do Estado de Alagoas   •    ANO VIII | Nº 1382 \\n\\nESTADO DE ALAGOAS\\n\\nPREFEITURA MUNICIPAL DE ATALAIA\\n\\n\\n\\nGABINETE DO PREFEITO\\n\\nPORTARIA Nº 0101/2020 DE, 25 DE SETEMBRO DE 2020.\\n\\n\\n\\nPORTARIA Nº 0101/2020 DE, 25 DE SETEMBRO DE 2020.\\nCONCEDE APOSENTADORIA VOLUNTÁRIA\\n\\nPOR IDADE E TEMPO DE CONTRIBUIÇÃO,\\n\\nCOM PROVENTOS INTEGRAIS.\\n\\n\\n\\nO PREFEITO DO MUNICÍPIO DE ATALAIA/AL, no uso de suas\\n\\natribuições e prerrogativas legais,\\n\\nTendo em vista o que consta no Processo Administrativo N.º\\n\\n017/2020, RESOLVE conceder Aposentadoria Voluntária por Idade e\\n\\nTempo de Contribuição, com tempo de serviço/contribuição de 30\\n\\nanos, 04 meses e 26 dias, trabalhados neste município, em favor da\\n\\nSra. MARIA DAS GRAÇAS LOPES VIEIRA, CPF n.º\\n\\n730.575.254-15, Matrícula de Nº: 144, ASSISTENTE\\n\\nADMINISTRATIVO, com jornada de trabalho de 40 horas semanais,\\n\\nda Secretaria Municipal de Saúde, do Quadro de Servidores de\\n\\nProvimento Efetivo do Poder Executivo Municipal, com proventos\\n\\nintegrais, calculados com base na última remuneração contributiva, na\\n\\nforma da lei, com paridade total, de acordo com o art. 3º da Emenda\\n\\nConstitucional n.º 47 de 05 de julho de 2005, Fórmula 85/95\\n\\npublicada no DOU em 06 de julho de 2005.\\n\\n\\n\\nDê-se ciência, registre-se, publique-se e cumpra-se.\\n\\n\\n\\nPREFEITURA MUNICIPAL DE ATALAIA/AL, EM, 25 DE\\n\\nSETEMBRO DE 2020.\\n\\n\\n\\nFRANCISCO LUIZ DE ALBUQUERQUE\\nPrefeito\\n\\n\\n\\nSUZANA ALBUQUERQUE DE MEDEIROS\\nPresidente – Atalaia-Prev\\n\\n\\n\\nA presente portaria foi publicada e registrada nesta Secretaria\\n\\nMunicipal de Administração e Recursos Humanos aos 25 (vinte e\\n\\ncinco) dias do mês de setembro de 2020.\\n\\n\\n\\nLUIZ GUSTAVO DE ALBUQUERQUE MORAIS\\nSecretário Municipal de Administração\\n\\nPublicado por:\\nLucas Morais de Melo\\n\\nCódigo Identificador:652C9D74\\n\\n\\nSECRETARIA MUNICIPAL DE ADMINISTRAÇÃO\\n\\nAVISO DE LICITAÇÃO\\n\\n\\n\\nAVISO DE LICITAÇÃO\\nTOMADA DE PREÇO N. 013/2020. OBJETO: Obras de engenharia\\n\\n– construção de 01 (creche) no Povoado Olhos D’agua, no Município\\n\\nde Atalaia/AL. Abertura: 14 de outubro de 2020, às 09:00h. Local:\\n\\nSala de Reuniões da Comissão Permanente de Licitação. Frisa-se que\\n\\na sessão será realizada seguindo os critérios de segurança\\n\\nestabelecidos pelo Ministério da Saúde, respeitando a distância de 1 e\\n\\n½ metro entre os interessados, higienização com álcool 70% não só do\\n\\nambiente como de todos participantes, e por fim será obrigatório o\\n\\nuso de máscaras descartáveis durante toda a sessão pelos interessado.\\n\\nFUNDAMENTAÇÃO LEGAL: Lei Federal nº 8.666/93 e suas\\n\\nalterações, LC 123/2006 e 147/2014. DISPONIBILIDADE DO\\n\\nEDITAL E INFORMAÇÕES: Comissão Permanente de Licitação,\\n\\nRua Fernando Gondim, n° 114, Centro, cidade de Atalaia/AL das\\n\\n08:00 às 12:00 horas ou através do E-mail:\\n\\nprefeituracpl.atalaia@gmail.com.\\n\\n\\n\\nAtalaia, 24 de Setembro de 2020.\\n\\n\\n\\nFÁTIMA LARISSA MARQUES DE OMENA\\nPresidente.\\n\\nPublicado por:\\nLucas Morais de Melo\\n\\nCódigo Identificador:4E34D4A8\",\n  \"data_publicacao\": \"2020-09-28\"\n}",
  "{\n  \"municipio\": \"BELÉM\",\n  \"id\": \"belem\",\n  \"cabecalho\": \"Alagoas , 28 de Setembro de 2020   •   Diário Oficial dos Municípios do Estado de Alagoas   •    ANO VIII | Nº 1382 \",\n  \"texto\": \"Alagoas , 28 de Setembro de 2020   •   Diário Oficial dos Municípios do Estado de Alagoas   •    ANO VIII | Nº 1382 \\n\\nESTADO DE ALAGOAS\\n\\nPREFEITURA MUNICIPAL DE BELÉM\\n\\n\\n\\nCOMISSÃO PERMANENTE DE LICITAÇÃO\\n\\nAVISO DE LICITAÇÃO - TOMADA DE PREÇOS Nº 005/2020\\n\\n\\n\\nTOMADA DE PREÇOS Nº 005/2020, do tipo menor preço global,\\n\\nsob a forma de execução indireta, no regime de empreitada por preço\\n\\nglobal. Objeto: terraplenagem, drenagem de águas pluviais e\\n\\npavimentação em paralelepípedo da Rua José Francisco Domingos da\\n\\nSilva, no Povoado Barro Vermelho, Belém, Alagoas. Data/Hora: 15\\n\\nde outubro de 2020, as 09h00min. O edital do processo encontra-se a\\n\\ndisposição dos interessados no setor de licitações, podendo ser\\n\\nsolicitado através do email: cplbelem@outlook.com.\\n\\nBelém/AL, 25 de setembro de 2020.\\n\\n\\n\\nLUCIVAN ALEXANDRINO DE BARROS\\nPresidente CPL\\n\\nPublicado por:\\nLucivan Alexandrino de Barros\\n\\nCódigo Identificador:A81F0411\",\n  \"data_publicacao\": \"2020-09-28\"\n}",
  "{\n  \"municipio\": \"BELO MONTE\",\n  \"id\": \"belo-monte\",\n  \"cabecalho\": \"Alagoas , 28 de Setembro de 2020   •   Diário Oficial dos Municípios do Estado de Alagoas   •    ANO VIII | Nº 1382 \",\n  \"texto\": \"Alagoas , 28 de Setembro de 2020   •   Diário Oficial dos Municípios do Estado de Alagoas   •    ANO VIII | Nº 1382 \\n\\nESTADO DE ALAGOAS\\n\\nPREFEITURA MUNICIPAL DE BELO MONTE\\n\\n\\n\\nPREFEITURA MUNICIPAL DE BELO MONTE\\n\\nPORTARIA Nº. 016/2020\\n\\n\\n\\nDispõe sobre a Concessão de PENSÃO POR\\n\\nMORTE pelo falecimento de servidor a GILSON\\n\\nVIEIRA DE MELO.\\n\\n\\n\\nO PREFEITO DO MUNICÍPIO DE BELO MONTE, ESTADO\\n\\nDE ALAGOAS, no uso de suas atribuições legais,\\n\\nCONSIDERANDO o resultado final do processo administrativo de\\n\\nnº. 2007001/2020, de concessão de Pensão por Morte pelo\\n\\nfalecimento de servidor;\\n\\nCONSIDERANDO a instrução deste Processo de Pensão por Morte\\n\\npelo falecimento de servidor, a fim de enviá-lo ao Tribunal de Contas\\n\\ndo Estado de Alagoas TCE/AL, para Homologação e Registro\\n\\nRESOLVE:\\nArt. 1º - Homologar a CONCESSÃO de Pensão por Morte pelo\\n\\nFalecimento da Servidora Auzenira Vieira de Melo, ao dependente Sr.\\n\\nGILSON VIEIRA DE MELO, a partir de 10 de julho de 2020,\\n\\ninscrito no CPF sob o n°. 133.885.334-15, único dependente da ex-\\n\\nsegurada do Fundo de Previdência Social do Município de Belo\\n\\nMonte – BELO MONTE-PREV, Considerando e as regras contidas\\n\\nno Art. 40 da CF, combinado com o Art. 4º da Lei Municipal nº.\\n\\n397/2018, com seus Proventos finais calculados no valor de R$\\n\\n1.254,00 (um mil, duzentos e cinquenta e quatro reais) mensais.\\n\\nConforme documentação constante no processo administrativo Nº.\\n\\n2007001/2020 do supracitado Instituto de Previdência.\\n\\nArt. 2º - Os recursos decorrentes da aplicação desta portaria correrão\\n\\nà conta do Fundo de Previdência Social do Município de Belo Monte,\\n\\no BELO MONTE-PREV\\n\\n\\n\\n\\n\\n\\nwww.diariomunicipal.com.br/ama                                                                                        3\\n\\n\\n\\nArt. 3º. Esta Portaria entra em vigor na data de sua publicação,\\n\\nrevogadas as disposições em contrário.\\n\\n\\n\\nBelo Monte/AL, 24 de Setembro de 2020.\\n\\n\\n\\nCLAUDEVAL SANTOS SANTANA\\nPrefeito\\n\\nPublicado por:\\nRafael Lima da Cruz\\n\\nCódigo Identificador:C094A3AA\\n\\n\\nPREFEITURA MUNICIPAL DE BELO MONTE\\n\\nEXTRATO DE CONTRATO\\n\\n\\n\\nContrato nº 50/2020, firmado em 11/08/2020, com a empresa\\n\\nMAQTRAL - MAQUINAS, PEÇAS E TRATORES DE ALAGOAS\\n\\nLTDA, inscrita no CNPJ nº 05.453.608/0002-76; Objeto: Aquisição\\n\\nde uma Colhedora de Forragens para atender as necessidades da\\n\\nSecretaria Municipal de Agricultura; Amparo: Pregão Presencial\\n\\n11/2020; Processo: 0727001/2020; Vigência: 03 (três) meses;\\n\\nCobertura Orçamentária: Fun. Prog.: 09.90.20.606.0010.1026 –\\n\\nAquisição de Equip. e Máquinas Pesadas / Ele. De Des.: 4.4.90.52 –\\n\\nEquip. e Material Permanente / Fonte: 0010; Valor: R$ 29.500,00;\\n\\nSignatários: pelo Contratante, Claudeval Santos Santana e, pelo\\n\\ncontratado, Magno Brito Oliveira.\\n\\n\\n\\nBelo Monte/AL, 24 de setembro de 2020\\n\\n\\n\\nCLAUDEVAL SANTOS SANTANA\\nPrefeito\\n\\nPublicado por:\\nRafael Lima da Cruz\\n\\nCódigo Identificador:96F32101\",\n  \"data_publicacao\": \"2020-09-28\"\n}",
  "{\n  \"municipio\": \"CANAPI\",\n  \"id\": \"canapi\",\n  \"cabecalho\": \"Alagoas , 28 de Setembro de 2020   •   Diário Oficial dos Municípios do Estado de Alagoas   •    ANO VIII | Nº 1382 \",\n  \"texto\": \"Alagoas , 28 de Setembro de 2020   •   Diário Oficial dos Municípios do Estado de Alagoas   •    ANO VIII | Nº 1382 \\n\\nESTADO DE ALAGOAS\\n\\nPREFEITURA MUNICIPAL DE CANAPI\\n\\n\\n\\nSECRETARIA MUNICIPAL DE SAÚDE\\n\\nTERMO DE HOMOLOGAÇÃO\\n\\n\\n\\nTERMO DE HOMOLOGAÇÃO\\n\\nRef. Pregão Eletrônico nº 21/2020.\\n\\nRegistro de Preços\\n\\n\\nO Prefeito do Município de Canapi, no uso de suas atribuições e\\n\\nprerrogativas, considerando legais os procedimentos adotados, e,\\n\\nainda, para que se produzam os devidos e legais efeitos,\\n\\n\\n\\nRESOLVE:\\n\\n\\nHOMOLOGAR o resultado da licitação sob a modalidade de Pregão\\n\\nEletrônico nº 21/2020 (BB nº 827455), cujo objeto é o REGISTRO\\n\\nDE PREÇOS PARA FUTURA E EVENTUAL AQUISIÇÃO DE\\n\\nOXIGÊNIO MEDICINAL, para atender as necessidades da\\n\\nSecretaria de Saúde do Município de Canapi/AL, em favor da\\n\\nempresa: ALEXANDRO SANTOS DA SILVA - EPP, inscrita no\\n\\nCNPJ: 05.329.135/0001-19, que na ocasião atendeu aos termos do\\n\\ninstrumento convocatório da licitação, para a execução do objeto\\n\\nlicitado, ficando a mesma convocada para assinatura da Ata de\\n\\nRegistro de Preços, nos termos do art. 64 caput, da lei nº 8.666/93, sob\\n\\nas penas da lei.\\n\\n\\n\\nCanapi/AL, 25 de setembro de 2020.\\n\\n\\n\\nVINICIUS JOSÉ MARIANO DE LIMA\\nPrefeito\\n\\nPublicado por:\\nEmerson de Souza Jatobá\\n\\nCódigo Identificador:35F35761\",\n  \"data_publicacao\": \"2020-09-28\"\n}",
  "{\n  \"municipio\": \"DELMIRO GOUVEIA\",\n  \"id\": \"delmiro-gouveia\",\n  \"cabecalho\": \"Alagoas , 28 de Setembro de 2020   •   Diário Oficial dos Municípios do Estado de Alagoas   •    ANO VIII | Nº 1382 \",\n  \"texto\": \"Alagoas , 28 de Setembro de 2020   •   Diário Oficial dos Municípios do Estado de Alagoas   •    ANO VIII | Nº 1382 \\n\\nESTADO DE ALAGOAS\\n\\nPREFEITURA MUNICIPAL DE DELMIRO GOUVEIA\\n\\n\\n\\nSECRETARIA MUNICIPAL DE ADMINISTRACAO\\n\\nHOMOLOGAÇÃO\\n\\n\\n\\nPROCESSO ADMINISTRATIVO N° 0319020/2020\\n\\nPREGÃO ELETRÔNICO N° 017/2020\\n\\nASSUNTO: Registro de preço para futura e eventual contratação de\\n\\nempresa especializada na prestação dos serviços continuados de\\n\\nrecarga de tonner e cartuchos de tintas.\\n\\n\\n\\nCom base nas informações: HOMOLOGO o presente, em favor da\\n\\nempresa:\\n\\nYURI DEMETRIUS NUNES SANTOS – ME CNPJ n°\\n\\n14.135.315/00001-50, vencedor dos lotes 01 e 02 com valor global de\\n\\nR$ 219.740,00 (Duzentos e dezenove mil setecentos e quarenta reais).\\n\\n\\n\\nDelmiro Gouveia – AL, 21 de Setembro de 2020.\\n\\n\\n\\nERALDO JOAQUIM CORDEIRO\\nPrefeito\\n\\nPublicado por:\\nAna Ligia da Silva Gomes\\n\\nCódigo Identificador:9A2A945C\\n\\n\\nSECRETARIA MUNICIPAL DE ADMINISTRACAO\\n\\nEXTRATO DE ATA DE REGISTRO DE PREÇO\\n\\n\\n\\nPROCESSO ADMINISTRATIVO N° 0319020/2020\\n\\nPREGÃO ELETRÔNICO N° 017/2020\\n\\nASSUNTO:Registro de preço para futura e eventual contratação de\\n\\nempresa especializada na prestação dos serviços continuados de\\n\\nrecarga de tonner e cartuchos de tintas.\\n\\nÓrgão Gerenciador: Município de Delmiro Gouveia - AL.\\n\\nFornecedor Beneficiário:YURI DEMETRIUS NUNES SANTOS –\\n\\nME CNPJ n° 14.135.315/00001-50.\\nVencedor dos lotes 01 e 02 com valor global de R$ 219.740,00\\n\\n(Duzentos e dezenove mil setecentos e quarenta reais).\\n\\nVigência: 12 (doze) meses.\\n\\n\\n\\nDelmiro Gouveia – AL, 21 de Setembro de 2020.\\n\\n\\n\\nERALDO JOAQUIM CORDEIRO\\nPrefeito\\n\\nPublicado por:\\nAna Ligia da Silva Gomes\\n\\nCódigo Identificador:5AC3BBC1\\n\\n\\nSECRETARIA MUNICIPAL DE ASSISTÊNCIA SOCIAL\\n\\nTERMO DE AJUSTE\\n\\n\\n\\nProcesso Administrativo n° 0709029/2020\\n\\nObjeto: Fornecimento de botijão de gás GLP de 13kg.\\n\\nContratante: Município de Delmiro Gouveia - AL.\\n\\nContratada: Capa Gás e Transportes Ltda CNPJ n° 13.584.130/0001-\\n\\n60.\\n\\nValor: R$ 4.424,41 (Quatro mil quatrocentos e vinte e quatro reais e\\n\\nquarenta e um centavos).\\n\\n\\n\\nERALDO JOAQUIM CORDEIRO\\nPrefeito\\n\\nPublicado por:\\nAna Ligia da Silva Gomes\\n\\nCódigo Identificador:0DF64903\\n\\n\\nSECRETARIA MUNICIPAL DE SAÚDE\\n\\nHOMOLOGAÇÃO\\n\\n\\n\\nPROCESSO ADMINISTRATIVO N° 0701-041/2020\\n\\nPREGÃO ELETRÔNICO N° 22/2020\\n\\nASSUNTO: Registro de preço para futura e eventual contração de\\n\\nempresa especializada na prestação dos serviços de sanitização com o\\n\\nfornecimento de mão de obra, todos os insumos, materiais,\\n\\nequipamentos e ferramentas necessárias, visando atender as\\n\\nnecessidades da Prefeitura Municipal de Delmiro Gouveia – AL.\\n\\n\\n\\n\\n\\n\\n\\n\\nwww.diariomunicipal.com.br/ama                                                                                        4\\n\\n\\n\\nCom base nas informações: HOMOLOGO o presente, em favor da\\n\\nempresa:\\n\\n\\n\\nM.C.A. SOUTO FILHO – ME, CNPJ N° 10.963.887/0001-77,\\n\\nvencedora dos lotes: Lote 01 – R$ 3.731.250,00 (Três milhões\\n\\nsetecentos e trinta e um mil duzentos e cinquenta reais) e Lote 02 – R$\\n\\n1.243.750,00 (Um milhão duzentos e quarenta e três mil setecentos e\\n\\ncinquenta reais). Valor Global R$ 4.975.000,00 (Quatro milhões\\n\\nnovecentos e setenta e cinco mil reais).\\n\\n\\n\\nDelmiro Gouveia – AL, 10 de Setembro de 2020.\\n\\n\\n\\nERALDO JOAQUIM CORDEIRO\\nPrefeito\\n\\nPublicado por:\\nAna Ligia da Silva Gomes\\n\\nCódigo Identificador:84236538\\n\\n\\nSECRETARIA MUNICIPAL DE SAÚDE\\n\\nEXTRATO DE ATA DE REGISTRO DE PREÇO\\n\\n\\n\\nPROCESSO ADMINISTRATIVO N° 0701-041/2020\\n\\nPREGÃO ELETRÔNICO N° 22/2020\\n\\nObjeto:Registro de preço para futura e eventual contração de empresa\\n\\nespecializada na prestação dos serviços de sanitização com o\\n\\nfornecimento de mão de obra, todos os insumos, materiais,\\n\\nequipamentos e ferramentas necessárias, visando atender as\\n\\nnecessidades da Prefeitura Municipal de Delmiro Gouveia – AL.\\n\\nÓrgão Gerenciador: Município de Delmiro Gouveia - AL.\\n\\nFornecedor Beneficiário: M.C.A. SOUTO FILHO – ME, CNPJ N°\\n\\n10.963.887/0001-77.\\n\\nVencedora dos lotes: Lote 01 – R$ 3.731.250,00 (Três milhões\\n\\nsetecentos e trinta e um mil duzentos e cinquenta reais) e Lote 02 – R$\\n\\n1.243.750,00 (Um milhão duzentos e quarenta e três mil setecentos e\\n\\ncinquenta reais). Valor Global R$ 4.975.000,00 (Quatro milhões\\n\\nnovecentos e setenta e cinco mil reais).\\n\\nVigência: 12 (Doze) meses.\\n\\n\\n\\nERALDO JOAQUIM CORDEIRO\\nPrefeito\\n\\nPublicado por:\\nAna Ligia da Silva Gomes\\n\\nCódigo Identificador:F33AB5C1\\n\\n\\nSECRETARIA MUNICIPAL DE SAÚDE\\n\\nEXTRATO DE CONTRATO\\n\\n\\n\\nProcesso Administrativo n° 0912012/2019 Pregão Eletrônico n°\\n\\n45/2019.\\n\\nObjeto: Aquisição de tonner, impressoras e recarga de tonner.\\n\\nContratante: Município de Delmiro Gouveia - AL.\\n\\nContratada: Yuri Demetrius Nunes Santos - ME CNPJ n°\\n\\n14.135.315/0001-50\\n\\nValor: 21.875,00 (Vinte e um mil oitocentos e setenta e cinco reais).\\n\\nVigência: 31 de dezembro de 2020.\\n\\n\\n\\nERALDO JOAQUIM CORDEIRO\\nPrefeito\\n\\nPublicado por:\\nAna Ligia da Silva Gomes\\n\\nCódigo Identificador:E950A0FA\",\n  \"data_publicacao\": \"2020-09-28\"\n}",
  "{\n  \"municipio\": \"GIRAU DO PONCIANO\",\n  \"id\": \"girau-do-ponciano\",\n  \"cabecalho\": \"Alagoas , 28 de Setembro de 2020   •   Diário Oficial dos Municípios do Estado de Alagoas   •    ANO VIII | Nº 1382 \",\n  \"texto\": \"Alagoas , 28 de Setembro de 2020   •   Diário Oficial dos Municípios do Estado de Alagoas   •    ANO VIII | Nº 1382 \\n\\nESTADO DE ALAGOAS\\n\\nPREFEITURA MUNICIPAL DE GIRAU DO PONCIANO\\n\\n\\n\\nSECRETARIA DE ADMINISTRAÇÃO E PLANEJAMENTO\\n\\nEXTRATO DO CONTRATO N°056/2020\\n\\n\\n\\nEXTRATO DO CONTRATO N°056/2020\\n\\nPROCESSO Nº 1.042/2020\\n\\nINTERESSADO: SECRETARIA MUNICIPAL DE SAÚDE\\n\\nASSUNTO: AQUISIÇÃO DE MATERIAIS HOSPITALARES\\n\\nPARA O MUNICÍPIO DE GIRAU DO PONCIANO/AL.\\n\\nDispensa de Licitação nº 031/2020; Objeto: Aquisição de materiais\\n\\nhospitalares para o Município de Girau do Ponciano/AL, nos termos\\n\\nda Lei N° 13.979/2020 que dispõe sobre as medidas para\\n\\nenfrentamento da emergência de saúde pública decorrente da\\n\\nPandemia de Coronavírus (COVID-19). Contratante: Município de\\n\\nGirau do Ponciano, CNPJ nº 12.207.536/0001-61; Contrato nº\\n\\n056/2020; Contratada: VAL MED PRODUTOS E EQUIPAMENTOS\\n\\nMÉDICOS E HOSPITALARES EIRELI-EPP, inscrita no CNPJ sob o\\n\\nnº 05.980.425/0001-28, com valor global de R$ 89.920,00 (oitenta e\\n\\nnove mil e novecentos e vinte reais); Data de assinatura: 21/09/2020.\\n\\nFundamento legal: leis nº. 13.979/2020 e 8.666/93, e Parecer Jurídico\\n\\nnº 310/2020.\\n\\n\\n\\nGirau do Ponciano/AL, 25 de setembro de 2020.\\n\\n\\nDAVID RAMOS DE BARROS\\nPrefeito\\n\\nPublicado por:\\nClaudevania Soares Rodrigues\\n\\nCódigo Identificador:73D7D811\",\n  \"data_publicacao\": \"2020-09-28\"\n}",
  "{\n  \"municipio\": \"IBATEGUARA\",\n  \"id\": \"ibateguara\",\n  \"cabecalho\": \"Alagoas , 28 de Setembro de 2020   •   Diário Oficial dos Municípios do Estado de Alagoas   •    ANO VIII | Nº 1382 \",\n  \"texto\": \"Alagoas , 28 de Setembro de 2020   •   Diário Oficial dos Municípios do Estado de Alagoas   •    ANO VIII | Nº 1382 \\n\\nESTADO DE ALAGOAS\\n\\nPREFEITURA MUNICIPAL DE IBATEGUARA\\n\\n\\n\\nSECRETAARIA MUNICIPAL DE ADMINISTRAÇÃO\\n\\nAVISO DE LICITAÇÃO\\n\\n\\n\\nA Prefeitura Municipal de Ibateguara, através de sua Pregoeira, avisa\\n\\nque realizará a licitação na MODALIDADE: Pregão Eletrônico nº\\n\\n009/2020. TIPO: Menor Preço Por Item. DATA E HORA: 07 de\\n\\noutubro de 2020 às 10h00min. LOCAL: http://bnc.org.br. OBJETO:\\n\\nContratação de empresa para aquisição de material de informática\\n\\npara atender as necessidades das Secretarias de Administração,\\n\\nEducação, Saúde e Assistência Social do Município de Ibateguara. O\\n\\nPregão acima será realizado no horário local. Edital acima, disponível\\n\\nna CPL ou por requisição através do e-mail:\\n\\ncplnovaibateguara@gmail.com ou pelo site:\\n\\nhttp://www.ibateguara.al.gov.br/.\\n\\n\\n\\nIbateguara (AL), 25 de setembro de 2020.\\n\\n\\n\\nANA CLÁUDIA DUDA\\nPregoeira\\n\\nPublicado por:\\nAna Claudia Duda\\n\\nCódigo Identificador:1D060FF6\",\n  \"data_publicacao\": \"2020-09-28\"\n}",
  "{\n  \"municipio\": \"INHAPI\",\n  \"id\": \"inhapi\",\n  \"cabecalho\": \"Alagoas , 28 de Setembro de 2020   •   Diário Oficial dos Municípios do Estado de Alagoas   •    ANO VIII | Nº 1382 \",\n  \"texto\": \"Alagoas , 28 de Setembro de 2020   •   Diário Oficial dos Municípios do Estado de Alagoas   •    ANO VIII | Nº 1382 \\n\\nESTADO DE ALAGOAS\\n\\nPREFEITURA MUNICIPAL DE INHAPI\\n\\n\\n\\nPREFEITURA MUNICIPAL DE INHAPI\\n\\nEXTRATO DO CONTRATO INHAPI Nº 32-2020\\n\\n\\n\\nProcesso Nº 2120/2020\\n\\nContratante: Município de Inhapi/AL\\n\\nContratado: RADS GESTÃO CONSULTORIA E PLANEJAMENTO\\n\\nLTDA\\n\\nCNPJ nº 24.144.217/0001-94\\n\\nObjeto: Contratação de empresa especializada na prestação de serviço\\n\\nde consultoria e assessoria para organização, normatização, criação de\\n\\nprojeto gráfico, design e diagramação livros em box.\\n\\nVigência: 31 (trinta e um) de dezembro do corrente ano\\n\\nValor Global: 38.000,00 (trinta e oito mil reais)\\n\\nSignatários: JOSÉ CÍCERO VIEIRA e STÉFANY MAIARA\\n\\nDANTAS DA SILVA\\n\\nCelebrado: em 22/09/2020\\n\\nPublicado por:\\nRodrigo Alves do Nascimento\\n\\nCódigo Identificador:FCB436BE\\n\\n\\n\\n\\n\\n\\n\\n\\nwww.diariomunicipal.com.br/ama                                                                                        5\",\n  \"data_publicacao\": \"2020-09-28\"\n}",
  "{\n  \"municipio\": \"LAGOA DA CANOA\",\n  \"id\": \"lagoa-da-canoa\",\n  \"cabecalho\": \"Alagoas , 28 de Setembro de 2020   •   Diário Oficial dos Municípios do Estado de Alagoas   •    ANO VIII | Nº 1382 \",\n  \"texto\": \"Alagoas , 28 de Setembro de 2020   •   Diário Oficial dos Municípios do Estado de Alagoas   •    ANO VIII | Nº 1382 \\n\\nESTADO DE ALAGOAS\\n\\nPREFEITURA MUNICIPAL DE LAGOA DA CANOA\\n\\n\\n\\nCOMISSÃO PERMANENTE DE LICITAÇÕES\\n\\nAVISO DE CONTINUIDADE DE LICITAÇÃO - TOMADA DE\\n\\nPREÇOS 004/2020\\n\\n\\n\\nA Comissão Permanente de Licitações do município de Lagoa da\\n\\nCanoa/AL, CONVOCA os interessados para dá continuidade a\\n\\nlicitação TP 004/2020, que tem como objeto a contratação de empresa\\n\\nespecializada para construção de academia de saúde da modalidade\\n\\nintermediária no Povoado Mata Limpa, localizado no Município de\\n\\nLagoa da Canoa – AL. DATA: 01/10/2020 as 09h00min no setor de\\n\\nlicitações, localizado na Praça Vereador Benício Alves de Oliveira,\\n\\ns/n, Centro, Lagoa da Canoa/AL. Informações através do email:\\n\\ncpl.canoa@gmail.com.\\n\\n\\n\\nLagoa da Canoa/AL, 25 de setembro de 2020.\\n\\n\\n\\nLUCIVAN ALEXANDRINO DE BARROS\\nPresidente CPL\\n\\nPublicado por:\\nLucivan Alexandrino de Barros\\n\\nCódigo Identificador:FA03C518\",\n  \"data_publicacao\": \"2020-09-28\"\n}",
  "{\n  \"municipio\": \"MARECHAL DEODORO\",\n  \"id\": \"marechal-deodoro\",\n  \"cabecalho\": \"Alagoas , 28 de Setembro de 2020   •   Diário Oficial dos Municípios do Estado de Alagoas   •    ANO VIII | Nº 1382 \",\n  \"texto\": \"Alagoas , 28 de Setembro de 2020   •   Diário Oficial dos Municípios do Estado de Alagoas   •    ANO VIII | Nº 1382 \\n\\nESTADO DE ALAGOAS\\n\\nPREFEITURA MUNICIPAL DE MARECHAL DEODORO\\n\\n\\n\\nSECRETARIA MUNICIPAL DE GESTÃO, DOS RECURSOS\\n\\nHUMANOS E DO PATRIMÔNIO\\n\\nRATIFICAÇÃO DA CONTRATAÇÃO\\n\\n\\n\\nRATIFICAÇÃO DA DISPENSA\\nTenho por satisfeitas as razões apresentadas pela Secretaria Municipal\\n\\nde Saúde, RATIFICO os entendimentos firmados ao tempo em que\\n\\nAUTORIZO a contratação da empresa VAL MED PRODUTOS E\\n\\nEQUIPAMENTOS MEDICOS HOSPITALAR EIRELI , pessoa\\n\\njurídica de direito privado, inscrito no CNPJ sob o nº\\n\\n05.980.425/0001-28 sediada na Rua Dom Jonas Batinga, n° 414, Ouro\\n\\nPreto , Arapiraca/AL. CEP: 57.301-130, no valor de R$ 1.980,00 (mil\\n\\ne novecentos e oitenta reais) visando a aquisição de termômetro para\\n\\na campanha de vacinação antirrábica canina e felina, sob os\\n\\nfundamentos do artigo 24, inciso V da Lei Federal Nº 8.666 de 21 de\\n\\njunho de 1993.\\n\\n\\n\\nPublique-se o presente despacho dentro do prazo de 5 (cinco) dias,\\n\\ncomo condição de eficácia dos atos.\\n\\nE por fim, considerando as determinações firmadas, seguem os autos\\n\\npara empenhar e providenciar a emissão da respectiva nota de\\n\\nempenho da supracitada Empresa, nos termos da ratificação.\\n\\n\\n\\nMarechal Deodoro/AL, 25 de setembro de 2020\\n\\n\\n\\nCLÁUDIO ROBERTO AYRES DA COSTA\\nPrefeito do Município de Marechal Deodoro/AL\\n\\nPublicado por:\\nMaria José Barbosa da Silva Filha\\n\\nCódigo Identificador:54167F14\\n\\n\\nSECRETARIA MUNICIPAL DE GESTÃO, DOS RECURSOS\\n\\nHUMANOS E DO PATRIMÔNIO\\n\\nEXTRATO - CONTRATO Nº 0307.008/2020 - FÊNIX\\n\\n\\n\\nCONTRATO Nº 0307.008/2020\\n\\nPartes: PREFEITURA MUNICIPAL DE MARECHAL\\n\\nDEODORO e FÊNIX LOCAÇÃO DE AUTOMÓVEIS EIRELI;\\n\\ninscrita no CNPJ nº 17.340.559/0001-63.\\n\\nObjeto: Prestação de serviços de Locação de Conjuntos Motobomba,\\n\\nmotor a diesel, para atender as demandas da Secretaria Municipal de\\n\\nObras e Infraestrutura por meio do Programa de Prevenção as Cheias\\n\\n– PREVINIR, no Município de Marechal Deodoro/AL.\\n\\nFundamentação Legal: Se regerá pelas disposições da Lei nº 8.666, de\\n\\n21 de junho de 1993, e demais normas legais aplicáveis.\\n\\nValor Total: R$ 31.500,00 (Trinta e um mil e quinhentos reais).\\n\\nData de Assinatura: 03 de julho de 2020.\\n\\nVigência: O prazo de vigência deste Termo de Contrato são de 3 (três)\\n\\nmeses, contados a partir da data de sua assinatura, prorrogável por\\n\\nperíodos sucessivos, enquanto perdurar a necessidade do Programa de\\n\\nPrevenção as Cheias - PREVINIR.\\n\\nSignatários:\\n\\nCláudio Roberto Ayres da Costa\\n\\nPREFEITURA MUNICIPAL DE MARECHAL DEODORO - AL\\n\\n– CONTRATANTE\\nVictor de Medeiros Almeida\\n\\nSECRETARIA MUNICIPAL DE OBRAS E\\n\\nINFRAESTRUTURA - INTERVENIENTE\\nMatheus Esteves Lima\\n\\nFÊNIX LOCAÇÃO DE AUTOMÓVEIS EIRELI –\\n\\nCONTRATADA\\n\\nPublicado por:\\nPriscylla Silva dos Santos\\n\\nCódigo Identificador:555552C2\\n\\n\\nSECRETARIA MUNICIPAL DE GESTÃO, DOS RECURSOS\\n\\nHUMANOS E DO PATRIMÔNIO\\n\\nEXTRATO - 3º T. ADITIVO - MARLUCE MARISA\\n\\n\\n\\n3º TERMO ADITIVO AO CONTRATO DE LOCAÇÃO DE\\n\\nIMÓVEL\\nPartes: PMMD e a Sra. MARLUCE MARISA ARAÚJO\\n\\nRODRIGUES, inscrita no CPF sob o nº 260.217.304-53.\\n\\nCLÁUSULA PRIMEIRA – DA VIGÊNCIA\\n\\nA vigência do contrato fica prorrogada até 31 de dezembro de 2020,\\n\\ncontados do encerramento da vigência do 2º Termo Aditivo.\\n\\nCLÁUSULA TERCEIRA – DA RATIFICAÇÃO\\n\\nPermanecem ratificadas as demais Cláusulas contratuais não alteradas\\n\\npelo presente Termo Aditivo.\\n\\nData de Assinatura: 28 de julho de 2020.\\n\\nSignatários:\\n\\nCláudio Roberto Ayres da Costa\\n\\nPREFEITURA MUNICIPAL DE MARECHAL DEODORO/AL –\\n\\nLOCATÁRIO\\n\\nCarlos Alberto Pimentel de Andrade Júnior\\n\\nSECRETARIA MUNICIPAL DE PLANEJAMENTO,\\n\\nORÇAMENTO E DESENVOLVIMENTO URBANO –\\n\\nINTERVENIENTE\\n\\nMarluce Marisa Araújo Rodrigues\\n\\nLOCADORA\\n\\nPublicado por:\\nPriscylla Silva dos Santos\\n\\nCódigo Identificador:BB4E80EC\\n\\n\\nSECRETARIA MUNICIPAL DE OBRAS E\\n\\nINFRAESTRUTURA\\n\\nAVISO DE LICITAÇÃO\\n\\n\\n\\nModalidade: CARTA CONVITE Nº 003/2020\\n\\nObjeto: Contratação de empresa de engenharia para a execução de\\n\\nserviços de recuperação da rede de esgoto do conjunto habitacional\\n\\nGislene Matheus, localizada em Marechal Deodoro/AL.\\n\\nTipo: Menor preço global. Data de realização: 06/10/2020, às\\n\\n10h00min (horário local).\\n\\nO edital encontra-se a disposição dos interessados através do site\\n\\noficial da Prefeitura Municipal de Marechal Deodoro, no endereço\\n\\neletrônico http://www.marechaldeodoro.al.gov.br/ . Os anexos estarão\\n\\ndisponíveis para aquisição no Setor de licitações da Secretaria\\n\\nMunicipal de Obras e Infraestrutura, localizado no Loteamento\\n\\nCidade Imperial, quadra A, Lote 7, Marechal Deodoro. Dúvidas\\n\\natravés do e-mail cplmarechaldeodoro@gmail.com, no horário de\\n\\n08h00min as 14h00min.\\n\\n\\n\\nMarechal Deodoro - Alagoas, 25 de setembro de 2020.\\n\\n\\n\\nTASSIANE CAVALCANTE BARROS\\nPresidente da CPL\\n\\n\\n\\n\\n\\n\\nwww.diariomunicipal.com.br/ama                                                                                        6\\n\\n\\n\\nPublicado por:\\nJair Barcelos Cerqueira\\n\\nCódigo Identificador:5BB4B24D\\n\\n\\nSECRETARIA MUNICIPAL DE OBRAS E\\n\\nINFRAESTRUTURA\\n\\nSÚMULA DO CONTRATO Nº 2204.001/2020\\n\\n\\n\\nERRATA\\n\\n\\n O Município de Marechal Deodoro, por meio da Comissão\\n\\nPermanente de Licitação, retifica a publicação do extrato do contrato\\n\\nnº 2204.001/2020, oriundo do processo licitatório nº 0211063/2020,\\n\\nTomada de Preços nº 01/2020, cujo objeto é a contratação de empresa\\n\\nespecializada para execução de serviços de engenharia para\\n\\nrestauração e adaptação da igreja do Rosário dos homens pretos,\\n\\nsituada no sítio histórico, no município de Marechal Deodoro,\\n\\npublicado no Diário Oficial do Estado - DOE, no dia 28 de abril de\\n\\n2020, Edição 1317, nos seguintes termos:\\n\\n\\n\\n ONDE SE LÊ:\\n\\n\\nO presente contrato terá vigência de 10 (dez) meses, contados a partir\\n\\nda publicação de seu extrato no Diário Oficial do Estado.\\n\\n\\n\\n LEIA-SE:\\n\\n\\nO presente contrato vigerá por 10 (dez) meses, contados a partir de\\n\\nsua assinatura, tendo sua eficácia a partir da publicação do extrato no\\n\\nDiário Oficial do estado, podendo ser prorrogado na forma do Art. 57\\n\\nda Lei Federal 8.666/93.\\n\\n\\n\\nMarechal Deodoro - Alagoas, 25 de setembro de 2020.\\n\\n\\n\\nTASSIANE CAVALCANTE BARROS\\nPresidente\\n\\n\\n\\nJOÃO FELIPE SANTOS DA ROCHA\\nMembro\\n\\n\\n\\nJAIR BARCELOS CERQUEIRA\\nMembro\\n\\n\\n\\nJOSÉ PETRÚCIO DOS SANTOS\\nMembro\\n\\nPublicado por:\\nJair Barcelos Cerqueira\\n\\nCódigo Identificador:84941F22\\n\\n\\nSERVIÇO AUTÔNOMO DE ÁGUA E ESGOTO - SAAE\\n\\nAVISO DE COTAÇÃO\\n\\n\\n\\nO SAAE - Serviço Autônomo de Água e Esgoto de Marechal\\n\\nDeodoro, Estado de Alagoas, através do seu setor de compras,\\n\\ninforma que está recebendo cotações para o processo abaixo descrito:\\n\\nProcesso Nº 546/2020; para envio das propostas: 05 (cinco) dias uteis,\\n\\na partir desta publicação. Objeto: Contratação de empresa\\n\\nespecializada para fornecimento de mobiliário para o Serviço\\n\\nAutônomo de Água e Esgoto do Município de Marechal Deodoro/AL.\\n\\nPara maiores informações no endereço: Rua Dr. Ladislau Neto, S/N -\\n\\nCentro - Marechal Deodoro - AL CEP: 57.160-000, Fone: (82) 3263-\\n\\n1159, ou pelo e-mail: saae.md@hotmail.com\\n\\n\\n\\nMarechal Deodoro, 24 de setembro de 2020.\\n\\n\\n\\nJOSE AGOSTINHO DOS SANTOS FILHO\\nDepartamento de Aquisição de Bens e Serviços\\n\\nPublicado por:\\nCaline Passos Costa\\n\\nCódigo Identificador:42ABCE0F\",\n  \"data_publicacao\": \"2020-09-28\"\n}",
  "{\n  \"municipio\": \"PÃO DE AÇÚCAR\",\n  \"id\": \"pao-de-acucar\",\n  \"cabecalho\": \"Alagoas , 28 de Setembro de 2020   •   Diário Oficial dos Municípios do Estado de Alagoas   •    ANO VIII | Nº 1382 \",\n  \"texto\": \"Alagoas , 28 de Setembro de 2020   •   Diário Oficial dos Municípios do Estado de Alagoas   •    ANO VIII | Nº 1382 \\n\\nESTADO DE ALAGOAS\\n\\nPREFEITURA MUNICIPAL DE PÃO DE AÇÚCAR\\n\\n\\n\\nSERVIÇO AUTÔNOMO DE ÁGUA E ESGOTO – SAAE\\n\\nTERMO DE RATIFICAÇÃO\\n\\n\\n\\nRatifico a Dispensa de Licitação 01/2020 para a aquisição de\\n\\nMateriais Hidráulicos para o SAAE, visando atender as necessidades\\n\\ndo Sistema Autônomo de Água e Esgoto – SAAE, fundamentada no\\n\\nart. 24, inciso V, da Lei nº 8666/93 e alterações. Empresa: Oliveira &\\n\\nSilva Distribuidora Ltda, inscrita no CNPJ/MF sob o nº\\n\\n29.261.608/0001-51. Valor R$ 155.633,25 (Cento e Cinquenta e\\n\\nCinco Mil Seiscentos e Trinta e Três Reais e Vinte e Cinco Centavos).\\n\\n\\n\\nPão de Açúcar - AL, 25 de setembro de 2020.\\n\\n\\n\\nABEL DA SILVA COSTA SOBRINHO\\nDiretor.\\n\\nPublicado por:\\nTiago Gomes dos Santos\\n\\nCódigo Identificador:69800CB8\",\n  \"data_publicacao\": \"2020-09-28\"\n}",
  "{\n  \"municipio\": \"PAULO JACINTO\",\n  \"id\": \"paulo-jacinto\",\n  \"cabecalho\": \"Alagoas , 28 de Setembro de 2020   •   Diário Oficial dos Municípios do Estado de Alagoas   •    ANO VIII | Nº 1382 \",\n  \"texto\": \"Alagoas , 28 de Setembro de 2020   •   Diário Oficial dos Municípios do Estado de Alagoas   •    ANO VIII | Nº 1382 \\n\\nESTADO DE ALAGOAS\\n\\nPREFEITURA MUNICIPAL DE PAULO JACINTO\\n\\n\\n\\nGABINETE DO PREFEITO\\n\\nPUBLICAÇÃO DE DESPACHO RATIFICADOR PROCESSO\\n\\nNº 08.03.0014/2020\\n\\n\\n\\nPUBLICAÇÃO DE DESPACHO RATIFICADOR\\n\\nProcesso nº 08.03.0014/2020\\n\\nInteressado(a): Secretaria Municipal de Obras e Serviços Urbanos\\n\\nAssunto: Contratação de empresa especializada em serviços de análise\\n\\nfísico-química e microbiológica.\\n\\nDECLARAÇÃO\\n\\n\\n\\nDECLARO para os devidos fins de direito, que em cumprimento as\\n\\nemanações das normas legais que tratam sobre finanças públicas, em\\n\\nespecial aos incisos I e II do artigo 16 da Lei Complementar N°\\n\\n101/2000, as despesas oriundas deste processo ora em tramitação, tem\\n\\nadequação orçamentária e financeira para o corrente exercício\\n\\nfinanceiro com a Lei Orçamentária Anual, e compatibilidade com o\\n\\nPlano Plurianual e com a Lei de Diretrizes Orçamentárias.\\n\\nRATIFICAÇÃO DA CONTRATAÇÃO:\\n\\nTenho por satisfeitas as razões apresentadas pela Secretaria Municipal\\n\\nde Obras e Serviços Urbanos, bem como, as informações procedentes\\n\\nda Procuradoria deste Município, RATIFICO os entendimentos\\n\\nfirmados ao tempo em que AUTORIZO a contratação da empresa\\n\\nTEIA SERVIÇOS AMBIENTAIS LTDA, pessoa jurídica de direito\\n\\nprivado, inscrita no CNPJ sob nº 11.553.614/0001-17, com sede na\\n\\nAvenida Álvaro Otacílio, nº 3731, Sala 102 Bloco B - Espanha,\\n\\nJatiúca, Maceió - AL, CEP 57.036-850, no valor de R$ 1.100,00 (mil\\n\\ne cem reais), para serviços de elaboração de relatório e análise físico-\\n\\nquímica e microbiológica, para a obra do Esgotamento Sanitário do\\n\\nConjunto Habitacional Francisco de Assis Barbosa.\\n\\nPublique-se o presente despacho dentro do prazo de 5 (cinco) dias,\\n\\ncomo condição de eficácia dos atos.\\n\\nE por fim, considerando as determinações firmadas, seguem os autos\\n\\npara empenhar e providenciar a emissão da respectiva nota de\\n\\nempenho da supracitada Empresa, nos termos da ratificação.\\n\\n\\n\\nPaulo Jacinto/AL, 25 de setembro de 2020.\\n\\n\\n\\nMARCOS ANTONIO DE ALMEIDA\\nPrefeito\\n\\nPublicado por:\\nCarlos Rogério Macedo Silva\\n\\nCódigo Identificador:F461DC06\\n\\n\\nGABINETE DO PREFEITO\\n\\nPUBLICAÇÃO DE DESPACHO RATIFICADOR PROCESSO\\n\\nNº 08.26.0006/2020\\n\\n\\n\\nPUBLICAÇÃO DE DESPACHO RATIFICADOR\\n\\nProcesso nº 08.26.0006/2020\\n\\nInteressado(a): Secretaria Municipal de Assistência Social Assunto:\\n\\nAquisição de Equipamentos de Proteção Individual – EPI’s.\\n\\n\\n\\n\\n\\n\\nwww.diariomunicipal.com.br/ama                                                                                        7\\n\\n\\n\\nDECLARAÇÃO\\n\\nDECLARO para os devidos fins de direito, que em cumprimento as\\n\\nemanações das normas legais que tratam sobre finanças públicas, em\\n\\nespecial aos incisos I e II do artigo 16 da Lei Complementar N°\\n\\n101/2000, as despesas oriundas deste processo ora em tramitação, tem\\n\\nadequação orçamentária e financeira para o corrente exercício\\n\\nfinanceiro com a Lei Orçamentária Anual, e compatibilidade com o\\n\\nPlano Plurianual e com a Lei de Diretrizes Orçamentárias.\\n\\n\\n\\nRATIFICAÇÃO DA CONTRATAÇÃO:\\n\\nTenho por satisfeitas as razões apresentadas pela Secretaria Municipal\\n\\nde Assistência Social, bem como, as informações procedentes da\\n\\nProcuradoria deste Município, RATIFICO os entendimentos firmados\\n\\nao tempo em que AUTORIZO a contratação da empresa LEANDRO\\n\\nFERRO TORRES 09719714476, pessoa jurídica de direito\\n\\nprivado,inscrita no CNPJ sob nº 36.720.866/0001-14, com sede na\\n\\nPraça da Independência, nº 142, Sala 13, Centro, Palmeira dos Índios\\n\\n- AL, CEP 57.600-010, no valor de R$ 6.200,00 (seis mil e duzentos\\n\\nreais), para aquisição de equipamentos de proteção individual – EPI’s,\\n\\npara atendimento das necessidades da Secretaria Municipal de\\n\\nAssistência Social.\\n\\nPublique-se o presente despacho dentro do prazo de 5 (cinco) dias,\\n\\ncomo condição de eficácia dos atos.\\n\\nE por fim, considerando as determinações firmadas, seguem os autos\\n\\npara empenhar e providenciar a emissão da respectiva nota de\\n\\nempenho da supracitada Empresa, nos termos da ratificação.\\n\\n\\n\\nPaulo Jacinto/AL, 25 de setembro de 2020.\\n\\n\\n\\nMARCOS ANTONIO DE ALMEIDA\\nPrefeito\\n\\nPublicado por:\\nCarlos Rogério Macedo Silva\\n\\nCódigo Identificador:1511BE2B\\n\\n\\nGABINETE DO PREFEITO\\n\\nPUBLICAÇÃO DE DESPACHO RATIFICADOR PROCESSO\\n\\nNº 08.17.0007/2020\\n\\n\\n\\nPUBLICAÇÃO DE DESPACHO RATIFICADOR\\n\\nProcesso nº 08.17.0007/2020\\n\\nInteressado(a): Secretaria Municipal de Assistência Social\\n\\nAssunto: Aquisição de Impressora.\\n\\nDECLARAÇÃO\\n\\n\\n\\nDECLARO para os devidos fins de direito, que em cumprimento as\\n\\nemanações das normas legais que tratam sobre finanças públicas, em\\n\\nespecial aos incisos I e II do artigo 16 da Lei Complementar N°\\n\\n101/2000, as despesas oriundas deste processo ora em tramitação, tem\\n\\nadequação orçamentária e financeira para o corrente exercício\\n\\nfinanceiro com a Lei Orçamentária Anual, e compatibilidade com o\\n\\nPlano Plurianual e com a Lei de Diretrizes Orçamentárias.\\n\\nRATIFICAÇÃO DA CONTRATAÇÃO:\\n\\nTenho por satisfeitas as razões apresentadas pela Secretaria Municipal\\n\\nde Assistência Social, bem como, as informações procedentes da\\n\\nProcuradoria deste Município, RATIFICO os entendimentos firmados\\n\\nao tempo em que AUTORIZO a contratação da empresa J.G. FERRO\\n\\nTORRES, pessoa jurídica de direito privado, inscrita no CNPJ sob nº\\n\\n32.724.552/0001-39, com sede na Av.\\n\\nGraciliano Ramos, nº 56, Paraíso, Palmeira dos Índios - AL, CEP\\n\\n57.602-130, no valor de R$ 1.699,00 (mil, seiscentos e noventa e nove\\n\\nreais), para aquisição de 01 (uma) impressora, cuja finalidade é o\\n\\natendimento e a ampliação das demandas do Serviço de Convivência e\\n\\nFortalecimento de Vínculos.\\n\\n\\n\\nPublique-se o presente despacho dentro do prazo de 5 (cinco) dias,\\n\\ncomo condição de eficácia dos atos.\\n\\n\\n\\nE por fim, considerando as determinações firmadas, seguem os autos\\n\\npara empenhar e providenciar a emissão da respectiva nota de\\n\\nempenho da supracitada Empresa, nos termos da ratificação.\\n\\n\\n\\nPaulo Jacinto/AL, 25 de setembro de 2020.\\n\\n\\n\\nMARCOS ANTONIO DE ALMEIDA\\nPrefeito\\n\\nPublicado por:\\nCarlos Rogério Macedo Silva\\n\\nCódigo Identificador:C2EE626C\\n\\n\\nGABINETE DO PREFEITO\\n\\nPUBLICAÇÃO DE DESPACHO RATIFICADOR PROCESSO\\n\\nNº 03.02.0035/2020\\n\\n\\n\\nPUBLICAÇÃO DE DESPACHO RATIFICADOR\\n\\nProcesso nº 03.02.0035/2020\\n\\nInteressado(a): Secretaria Municipal de Administração e Finanças\\n\\nAssunto: Aquisição de Impressora Multifuncional.\\n\\n\\n\\nDECLARAÇÃO\\n\\n\\n\\nDECLARO para os devidos fins de direito, que em cumprimento as\\n\\nemanações das normas legais que tratam sobre finanças públicas, em\\n\\nespecial aos incisos I e II do artigo 16 da Lei Complementar N°\\n\\n101/2000, as despesas oriundas deste processo ora em tramitação, tem\\n\\nadequação orçamentária e financeira para o corrente exercício\\n\\nfinanceiro com a Lei Orçamentária Anual, e compatibilidade com o\\n\\nPlano Plurianual e com a Lei de Diretrizes Orçamentárias.\\n\\nRATIFICAÇÃO DA CONTRATAÇÃO:\\n\\nTenho por satisfeitas as razões apresentadas pela Secretaria Municipal\\n\\nde Administração e Finanças, bem como, as informações procedentes\\n\\nda Procuradoria deste Município, RATIFICO os entendimentos\\n\\nfirmados ao tempo em que AUTORIZO a contratação da empresa\\n\\nSUPRIFITAS LTDA, pessoa jurídica de direito privado, inscrita no\\n\\nCNPJ sob nº 35.772.974/0001-63, com sede na Rua Barão de Atalaia,\\n\\nnº 234, Centro, Maceió - AL, CEP 57.020-510, no valor de R$\\n\\n1.369,00 (mil, trezentos e sessenta e nove reais), para aquisição de 01\\n\\n(uma) impressora multifuncional, para desenvolvimento das\\n\\natividades da Junta Militar do Município de Paulo Jacinto.\\n\\nPublique-se o presente despacho dentro do prazo de 5 (cinco) dias,\\n\\ncomo condição de eficácia dos atos.\\n\\nE por fim, considerando as determinações firmadas, seguem os autos\\n\\npara empenhar e providenciar a emissão da respectiva nota de\\n\\nempenho da supracitada Empresa, nos termos da ratificação.\\n\\n\\n\\nPaulo Jacinto/AL, 25 de setembro de 2020.\\n\\n\\n\\nMARCOS ANTONIO DE ALMEIDA\\nPrefeito\\n\\nPublicado por:\\nCarlos Rogério Macedo Silva\\n\\nCódigo Identificador:57A972DD\\n\\n\\nGABINETE DO PREFEITO\\n\\nPUBLICAÇÃO DE DESPACHO RATIFICADOR PROCESSO\\n\\nNº 08.27.0009/2020\\n\\n\\n\\nPUBLICAÇÃO DE DESPACHO RATIFICADOR\\n\\n\\n\\nProcesso nº 08.27.0009/2020\\n\\nInteressado(a): Secretaria Municipal de Saúde\\n\\nAssunto: Custeio de Exame de Ressonância Magnética da Pelve com\\n\\nContraste.\\n\\n\\n\\nDECLARAÇÃO\\n\\n\\n\\nDECLARO para os devidos fins de direito, que em cumprimento as\\n\\nemanações das normas legais que tratam sobre finanças públicas, em\\n\\nespecial aos incisos I e II do artigo 16 da Lei Complementar N°\\n\\n101/2000, as despesas oriundas deste processo ora em tramitação, tem\\n\\nadequação orçamentária e financeira para o corrente exercício\\n\\nfinanceiro com a Lei Orçamentária Anual, e compatibilidade com o\\n\\nPlano Plurianual e com a Lei de Diretrizes Orçamentárias.\\n\\nRATIFICAÇÃO DA CONTRATAÇÃO: Tenho por satisfeitas as\\n\\nrazões apresentadas pela Secretaria Municipal de Saúde, bem como,\\n\\nas informações procedentes da Procuradoria deste Município,\\n\\nRATIFICO os entendimentos firmados ao tempo em que AUTORIZO\\n\\na contratação da empresa NOVA IMAGEM DIAGNÓSTICO POR\\n\\n\\n\\n\\n\\n\\nwww.diariomunicipal.com.br/ama                                                                                        8\\n\\n\\n\\nIMAGEM LTDA, pessoa jurídica de direito privado, inscrita no CNPJ\\n\\nsob nº 05.064.187/0001-00, com sede na\\n\\nRua Augusta, nº 285,Centro, Maceió - AL, CEP 57.020-010, no valor\\n\\nde R$ 700,00 (setecentos reais), para custeio de Exame de\\n\\nRessonância Magnética da Pelve com contraste, para a paciente do\\n\\nSUS, Priscila Santos do Nascimento, tendo em vista que a demanda\\n\\npelo CORA é insuficiente para atender a todos os pacientes em tempo\\n\\nhábil.\\n\\n\\n\\nPublique-se o presente despacho dentro do prazo de 5 (cinco) dias,\\n\\ncomo condição de eficácia dos atos.\\n\\n\\n\\nE por fim, considerando as determinações firmadas, seguem os autos\\n\\npara empenhar e providenciar a emissão da spectiva nota de empenho\\n\\nda supracitada Empresa, nos termos da ratificação.\\n\\n\\n\\nPaulo Jacinto/AL, 25 de setembro de 2020.\\n\\n\\n\\nMARCOS ANTONIO DE ALMEIDA\\nPrefeito\\n\\nPublicado por:\\nCarlos Rogério Macedo Silva\\n\\nCódigo Identificador:72170C5F\",\n  \"data_publicacao\": \"2020-09-28\"\n}",
  "{\n  \"municipio\": \"PILAR\",\n  \"id\": \"pilar\",\n  \"cabecalho\": \"Alagoas , 28 de Setembro de 2020   •   Diário Oficial dos Municípios do Estado de Alagoas   •    ANO VIII | Nº 1382 \",\n  \"texto\": \"Alagoas , 28 de Setembro de 2020   •   Diário Oficial dos Municípios do Estado de Alagoas   •    ANO VIII | Nº 1382 \\n\\nESTADO DE ALAGOAS\\n\\nPREFEITURA MUNICIPAL DE PILAR\\n\\n\\n\\nSECRETARIA MUNICIPAL DE ADMINISTRACAO\\n\\nEXONERAÇÃO À PEDIDO\\n\\n\\n\\nO Prefeito do Município de Pilar, Estado de Alagoas, no uso das\\n\\natribuições que lhe são conferidas pelo artigo 62, inciso XXI, da Lei\\n\\nOrgânica do Município datada de 05 de abril de 1990.\\n\\n\\n\\nRESOLVE EXONERAR\\n\\nA pedido o Sr. LUIS CARLOS DE LIMA SILVA, matricula nº\\n\\n20.817, CPF nº 041.667.694-48, ocupante do cargo/função Agente de\\n\\nEdemias, lotado na Secretaria Municipal de Saúde, conforme processo\\n\\nde requerimento apresentado no dia 25/09/2020, sob nº 0925-\\n\\n0005/2020.\\n\\n\\n\\nDê-se ciência, Publique-se.\\n\\n\\n\\nPilar/AL, 28 de setembro de 2020.\\n\\n\\n\\nRENATO REZENDE ROCHA FILHO\\nPrefeito\\n\\nPublicado por:\\nOsvaldo Lourenço da Silva Junior\\n\\nCódigo Identificador:F9CCB13D\",\n  \"data_publicacao\": \"2020-09-28\"\n}",
  "{\n  \"municipio\": \"PIRANHAS\",\n  \"id\": \"piranhas\",\n  \"cabecalho\": \"Alagoas , 28 de Setembro de 2020   •   Diário Oficial dos Municípios do Estado de Alagoas   •    ANO VIII | Nº 1382 \",\n  \"texto\": \"Alagoas , 28 de Setembro de 2020   •   Diário Oficial dos Municípios do Estado de Alagoas   •    ANO VIII | Nº 1382 \\n\\nESTADO DE ALAGOAS\\n\\nPREFEITURA MUNICIPAL DE PIRANHAS\\n\\n\\n\\nGABINETE DA PREFEITA\\n\\nEXTRATO DE HOMOLOGAÇÃO PREGÃO ELETRÔNICO Nº\\n\\n19/2020\\n\\n\\n\\nA Prefeitura Municipal de Piranhas/AL, torna público o resultado da\\n\\nLicitação referente ao PE nº 19/2020, registrado no sistema\\n\\nLicitações-e sob o nº 982841, o qual foi homologado, no valor de R$\\n\\n79.335,00 (setenta e nove mil e trezentos e trinta e cinco reais),\\n\\nreferente ao processo administrativo nº 0715014/2019, que tem por\\n\\nobjeto aquisição de medicamentos.\\n\\n\\n\\nInformações gerais: Os documentos pertinentes à licitação, em\\n\\ncomento, encontram-se disponibilizados para consulta no sítio\\n\\nwww.transparencia.piranhas.al.gov.br\\n\\n\\n\\n\\n\\nEXTRATO CONTRATO P.E. nº 19.1/2020\\n\\n\\nREF.: PREGÃO ELETRONICO nº 19 de 2020; OBJETO:\\n\\nCONTRATAÇÃO DE EMPRESA PARA AQUISIÇÃO DE\\n\\nMEDICAMENTOS; FORNECEDORA REGISTRADA: GLORIA\\n\\nFARMA DISTRIBUIDORA EIRELI, inscrita no CNPJ/MF sob o\\n\\nnº. 10.436.883/0001-30. PERÍODO DE VIGÊNCIA: 12 MESES;\\n\\nMENOR PREÇO POR LOTE, COM O VALOR TOTAL DE R$\\n\\n14.910,00 (catorze mil e novecentos e dez mil). SIGNATÁRIOS:\\n\\nMaristela Sena Dias, pelo Órgão Gerenciador e Maria Ivone Oliveira,\\n\\npela Fornecedora Registrada.\\n\\n\\n\\nEXTRATO CONTRATO P.E. nº 19.2/2020\\n\\n\\nREF.: PREGÃO ELETRONICO nº 19 de 2020; OBJETO:\\n\\nCONTRATAÇÃO DE EMPRESA PARA AQUISIÇÃO DE\\n\\nMEDICAMENTOS; FORNECEDORA REGISTRADA: MEDICAH\\n\\nCOMERCIO DE MEDICAMENTOS EIRELI, inscrita no\\n\\nCNPJ/MF sob o nº. 11.195.977/0001-28. PERÍODO DE VIGÊNCIA:\\n\\n12 MESES; MENOR PREÇO POR LOTE, COM O VALOR TOTAL\\n\\nDE R$ 8.105,00 (Oito mil e cento e cinco reais). SIGNATÁRIOS:\\n\\nMaristela Sena Dias, pelo Órgão Gerenciador e Anna Paula Aragão\\n\\nDantas de Oliveira, pela Fornecedora Registrada.\\n\\n\\n\\nEXTRATO CONTRATO P.E. nº 19.3/2020\\n\\n\\nREF.: PREGÃO ELETRONICO nº 19 de 2020; OBJETO:\\n\\nCONTRATAÇÃO DE EMPRESA PARA AQUISIÇÃO DE\\n\\nMEDICAMENTOS; FORNECEDORA REGISTRADA: ALCANCE\\n\\nNORDESTE, COMERCIO IMPORTAÇÃO & RXPORTAÇÃO\\n\\nDE MEDICAMENTOS EIRELI, inscrita no CNPJ/MF sob o nº.\\n\\n13.630.407/0001-44. PERÍODO DE VIGÊNCIA: 12 MESES;\\n\\nMENOR PREÇO POR LOTE, COM O VALOR TOTAL DE R$\\n\\n1.200,00 (Mil e duzentos reais). SIGNATÁRIOS: Maristela Sena\\n\\nDias, pelo Órgão Gerenciador e Fabiano Rodrigues de Andrade, pela\\n\\nFornecedora Registrada.\\n\\n\\n\\nEXTRATO CONTRATO P.E. nº 19.4/2020\\n\\n\\nREF.: PREGÃO ELETRONICO nº 19 de 2020; OBJETO:\\n\\nCONTRATAÇÃO DE EMPRESA PARA AQUISIÇÃO DE\\n\\nMEDICAMENTOS; FORNECEDORA REGISTRADA: MED\\n\\nFARMACE DISTRIBUIDORA DE MEDICAMENTOS LTDA,\\n\\ninscrita no CNPJ/MF sob o nº. 69.950.913/0001-75. PERÍODO DE\\n\\nVIGÊNCIA: 12 MESES; MENOR PREÇO POR LOTE, COM O\\n\\nVALOR TOTAL DE R$ 55.140,00 (cinquenta e cinco mil e cento e\\n\\nquarenta reais). SIGNATÁRIOS: Maristela Sena Dias, pelo Órgão\\n\\nGerenciador e Lucas Henrique de Melo Silva, pela Fornecedora\\n\\nRegistrada.\\n\\nPublicado por:\\nWellington Pinto Oliveira\\n\\nCódigo Identificador:6A70C2A4\\n\\n\\nGABINETE DA PREFEITA\\n\\nEXTRATO DE HOMOLOGAÇÃO PREGÃO ELETRÔNICO Nº\\n\\n03/2020\\n\\n\\n\\nA Prefeitura Municipal de Piranhas/AL, torna público o resultado da\\n\\nLicitação referente ao PE nº 03/2020, registrado no sistema\\n\\nLicitações-e sob o nº 982841, o qual foi homologado, no valor de R$\\n\\n745.978,99 (setecentos e quarenta e cinco mil, novecentos e setenta e\\n\\noito reais e noventa e nove centavos), referente ao processo\\n\\nadministrativo nº 0607009/2019, que tem por objeto Fornecimento de\\n\\nMaterial Médico Hospitalar.\\n\\n\\n\\nInformações gerais: Os documentos pertinentes à licitação, em\\n\\ncomento, encontram-se disponibilizados para consulta no sítio\\n\\nwww.transparencia.piranhas.al.gov.br\\n\\n\\n\\nEXTRATO CONTRATO P.E. nº 03.1/2020\\n\\n\\nREF.: PREGÃO ELETRONICO nº 03 de 2020; OBJETO:\\n\\nFORNECIMENTO DE MATERIAL MÉDICO HOSPITALAR;\\n\\nFORNECEDORA REGISTRADA: MEDICAH COMÉRCIO DE\\n\\nMEDICAMENTOS EIRELI, inscrita no CNPJ/MF sob o nº.\\n\\n11.195.977/0001-28. PERÍODO DE VIGÊNCIA: 31/12/2020;\\n\\n\\n\\n\\n\\n\\nwww.diariomunicipal.com.br/ama                                                                                        9\\n\\n\\n\\nMENOR PREÇO POR LOTE, COM O VALOR TOTAL DE R$\\n\\n235.234,84 (duzentos e trinta e cinco mil, duzentos e trinta e quatro\\n\\nreais e oitenta e quatro centavos). SIGNATÁRIOS: Maristela Sena\\n\\nDias, pelo Órgão Gerenciador e Anna Paula Aragão Dantas de\\n\\nOliveira, pela Fornecedora Registrada.\\n\\n\\n\\nEXTRATO CONTRATO P.E. nº 03.3/2020\\n\\n\\nREF.: PREGÃO ELETRONICO nº 03 de 2020; OBJETO:\\n\\nFORNECIMENTO DE MATERIAL MÉDICO HOSPITALAR;\\n\\nFORNECEDORA REGISTRADA: BIODIAG DIAGNOSTICA E\\n\\nHOSPITALAR LTDA, inscrita no CNPJ/MF sob o nº.\\n\\n20.273.404/0001-66. PERÍODO DE VIGÊNCIA: 31/12/2020;\\n\\nMENOR PREÇO POR LOTE, COM O VALOR TOTAL DE R$\\n\\n78.996,00 (Setenta e oito mil e novecentos e noventa e seis reais).\\n\\nSIGNATÁRIOS: Maristela Sena Dias, pelo Órgão Gerenciador e\\n\\nEdmilson Souza Monteiro, pela Fornecedora Registrada.\\n\\n\\n\\nEXTRATO CONTRATO P.E. nº 03.4/2020\\n\\n\\nREF.: PREGÃO ELETRONICO nº 03 de 2020; OBJETO:\\n\\nFORNECIMENTO DE MATERIAL MÉDICO HOSPITALAR;\\n\\nFORNECEDORA REGISTRADA: YVMED PRODUTOS\\n\\nFARMACÊUTICOS HOSPITALARES-EIRELI, inscrita no\\n\\nCNPJ/MF sob o nº. 21.949.562/0001-56. PERÍODO DE VIGÊNCIA:\\n\\n31/12/2020; MENOR PREÇO POR LOTE, COM O VALOR TOTAL\\n\\nDE R$ 222.333,40 (duzentos e vinte e dois mil e trezentos e trinta e\\n\\ntrês reais e quarenta centavos). SIGNATÁRIOS: Maristela Sena Dias,\\n\\npelo Órgão Gerenciador e Yuri Lindemberg Oliveira de Jesus, pela\\n\\nFornecedora Registrada.\\n\\n\\n\\nEXTRATO CONTRATO P.E. nº 03.5/2020\\n\\n\\nREF.: PREGÃO ELETRONICO nº 03 de 2020; OBJETO:\\n\\nFORNECIMENTO DE MATERIAL MÉDICO HOSPITALAR;\\n\\nFORNECEDORA REGISTRADA: TEMPO COMERCIAL\\n\\nDISTRIBUIDORA DE MEDICAMENTOS EIRELI, inscrita no\\n\\nCNPJ/MF sob o nº. 24.564.626/0001-99. PERÍODO DE VIGÊNCIA:\\n\\n31/12/2020; MENOR PREÇO POR LOTE, COM O VALOR TOTAL\\n\\nDE R$ 79.639,00 (setenta e nove mil e seiscentos e trinta e nove\\n\\nreais). SIGNATÁRIOS: Maristela Sena Dias, pelo Órgão Gerenciador\\n\\ne Givaldo Vieira de Santana, pela Fornecedora Registrada.\\n\\n\\n\\nEXTRATO CONTRATO P.E. nº 03.6/2020\\n\\n\\nREF.: PREGÃO ELETRONICO nº 03 de 2020; OBJETO:\\n\\nFORNECIMENTO DE MATERIAL MÉDICO HOSPITALAR;\\n\\nFORNECEDORA REGISTRADA: SO SAUDE PRODUTOS\\n\\nHOSPITALAR EIRELI, inscrita no CNPJ/MF sob o nº.\\n\\n29.775.313/0001-01. PERÍODO DE VIGÊNCIA: 31/12/2020;\\n\\nMENOR PREÇO POR LOTE, COM O VALOR TOTAL DE R$\\n\\n3.519,87 (três mil, quinhentos e dezenove reais e oitenta e sete\\n\\ncentavos). SIGNATÁRIOS: Maristela Sena Dias, pelo Órgão\\n\\nGerenciador e Ana Carolina da Fonte Oliveira Andrade, pela\\n\\nFornecedora Registrada.\\n\\n\\n\\nEXTRATO CONTRATO P.E. nº 03.7/2020\\n\\n\\nREF.: PREGÃO ELETRONICO nº 03 de 2020; OBJETO:\\n\\nFORNECIMENTO DE MATERIAL MÉDICO HOSPITALAR;\\n\\nFORNECEDORA REGISTRADA: C.O. DE SOUZA, inscrita no\\n\\nCNPJ/MF sob o nº. 30.788.967/0001-40. PERÍODO DE VIGÊNCIA:\\n\\n31/12/2020; MENOR PREÇO POR LOTE, COM O VALOR TOTAL\\n\\nDE R$ 90.356,70 (noventa mil, trezentos e cinquenta e seis reais e\\n\\ncinquenta centavos). SIGNATÁRIOS: Maristela Sena Dias, pelo\\n\\nÓrgão Gerenciador e Cleocina Oliveira de Souza, pela Fornecedora\\n\\nRegistrada.\\n\\nPublicado por:\\nWellington Pinto Oliveira\\n\\nCódigo Identificador:A470C504\",\n  \"data_publicacao\": \"2020-09-28\"\n}",
  "{\n  \"municipio\": \"POÇO DAS TRINCHEIRAS\",\n  \"id\": \"poco-das-trincheiras\",\n  \"cabecalho\": \"Alagoas , 28 de Setembro de 2020   •   Diário Oficial dos Municípios do Estado de Alagoas   •    ANO VIII | Nº 1382 \",\n  \"texto\": \"Alagoas , 28 de Setembro de 2020   •   Diário Oficial dos Municípios do Estado de Alagoas   •    ANO VIII | Nº 1382 \\n\\nESTADO DE ALAGOAS\\n\\nPREFEITURA MUNICIPAL DE POÇO DAS TRINCHEIRAS\\n\\n\\n\\nCOMISSÃO PERMANENTE DE LICITAÇÃO\\n\\nAVISO DE CHAMADA PÚBLICA Nº 02/2020\\n\\n\\n\\nEDITAL DE FOMENTO À CULTURA – LEI ALDIR BLANC\\n\\n\\nA Prefeitura Municipal de Poço das Trincheiras, através da Secretaria\\n\\nMunicipal de Cultura e Esporte torna público que se encontra à\\n\\ndisposição dos interessados, no Portal da Transparência através do\\n\\nlink: http://pocodastrincheiras.al.gov.br, o Edital da Chamada Pública\\n\\nnº 02/2020, referente ao Cadastramento de atores culturais que serão\\n\\nfomentados nos mais diversos campos de atuação cultural, como:\\n\\nprodução de lives, oficinas culturais, premiações fotográficas e\\n\\npublicações, em período definido imediatamente pela Secretaria\\n\\nMunicipal de Cultura e Esporte, tem como objetivo minimizar os\\n\\nefeitos do atual cenário de crise sanitária que assola a humanidade,\\n\\ncausada pela pandemia do novo CORONAVÍRUS/COV ID- 19. As\\n\\ninscrições poderão ser realizadas no período de 28 de setembro a 13\\n\\nde outubro de 2020, em dias corridos, exclusivamente na sede da\\n\\nSecretaria Municipal de Cultura e Esporte de Poço das Trincheiras.\\n\\nFUNDAMENTAÇÃO LEGAL: Lei Federal de Número 14.017/2020\\n\\nintitulada Aldir Blanc e da Medida Provisória de Número nº 990, de\\n\\n9/7/2020, que dispõem sobre o auxílio emergencial da cultura como\\n\\nmedida para enfrentamento da crise de saúde pública decorrente da\\n\\nCOVID-19 (corona vírus). DEMAIS INFORMAÇÕES: E-mail:\\n\\nCultura_pt@outlook.com.\\n\\n\\n\\nRENATA CAVALCANTE DA SILVA\\nPresidente da CPL\\n\\nPublicado por:\\nRailma Alencar Correia da Silva\\n\\nCódigo Identificador:186FDB51\",\n  \"data_publicacao\": \"2020-09-28\"\n}",
  "{\n  \"municipio\": \"PORTO CALVO\",\n  \"id\": \"porto-calvo\",\n  \"cabecalho\": \"Alagoas , 28 de Setembro de 2020   •   Diário Oficial dos Municípios do Estado de Alagoas   •    ANO VIII | Nº 1382 \",\n  \"texto\": \"Alagoas , 28 de Setembro de 2020   •   Diário Oficial dos Municípios do Estado de Alagoas   •    ANO VIII | Nº 1382 \\n\\nESTADO DE ALAGOAS\\n\\nPREFEITURA MUNICIPAL DE PORTO CALVO\\n\\n\\n\\nSECRETARIA MUNICIPAL DE CULTURA\\n\\nCHAMADA PÚBLICA\\n\\n\\n\\nEDITAL DE CREDENCIAMENTO DE FOMENTO À\\n\\nCULTURA BERNADETE LEITE\\nChamada Pública nº 003/2020. OBJETO: Cadastramento de atores\\n\\nculturais que serão fomentados nos mais diversos campos de atuação\\n\\ncultural, como: produção de lives, vídeoclipes, documentários,\\n\\namostra popular de dança, produções bibliográficas, festival de\\n\\nliteratura popular, oficinas culturais, premiações fotográficas e\\n\\nartísticas, em período definido imediatamente pela Secretaria\\n\\nMunicipal de Cultura, tem como objetivo minimizar os efeitos do\\n\\natual cenário de crise sanitária que assola a humanidade, causada pela\\n\\npandemia do novo CORONAVÍRUS/COVID- 19. Período de\\n\\nInscrição: 29/09/2020 à 07/10/2020, Análise das Propostas de 08 à\\n\\n14/10/2020, Divulgação do Resultado Final 15/10/2020. Local: na\\n\\nsala da Comissão Permanente de Licitação, localizada na Rua Dr.\\n\\nAntonio Dorta, nº 18 – Centro – Porto Calvo – AL.\\n\\nFUNDAMENTAÇÃO LEGAL: Lei 14.017/2020, Médida Provisória\\n\\nnº 990/2020 e Lei nº 8.666/93 e suas alterações posteriores.\\n\\nINFORMAÇÕES: A Chamada encontra-se disponível no endereço\\n\\nacima citado das 08:00 hs às 12:00 hs, ou pelo email:\\n\\ncplportocalvo@hotmail.com.\\n\\n\\n\\nPorto Calvo/AL, 28 de setembro de 2020.\\n\\n\\n\\nJOSÉ CARLOS DA FONSECA SILVA JUNIOR\\nPresidente da CPL\\n\\nPublicado por:\\nFlavio Henrique da Rocha Oliveira\\n\\nCódigo Identificador:67B458AE\",\n  \"data_publicacao\": \"2020-09-28\"\n}",
  "{\n  \"municipio\": \"QUEBRANGULO\",\n  \"id\": \"quebrangulo\",\n  \"cabecalho\": \"Alagoas , 28 de Setembro de 2020   •   Diário Oficial dos Municípios do Estado de Alagoas   •    ANO VIII | Nº 1382 \",\n  \"texto\": \"Alagoas , 28 de Setembro de 2020   •   Diário Oficial dos Municípios do Estado de Alagoas   •    ANO VIII | Nº 1382 \\n\\nESTADO DE ALAGOAS\\n\\nPREFEITURA MUNICIPAL DE QUEBRANGULO\\n\\n\\n\\nCOMISSÃO PERMANENTE DE LICITAÇÃO\\n\\nAVISO DE LICITAÇÃO\\n\\n\\n\\n\\n\\n\\n\\n\\nwww.diariomunicipal.com.br/ama                                                                                        10\\n\\n\\n\\nA PREFEITURA MUNICIPAL DE QUEBRANGULO torna público\\n\\naos interessados a realização da licitação na modalidade Pregão\\n\\nEletrônico de Nº 010/2020 - SRP, do tipo menor preço por item.\\n\\nObjeto: aquisição de Câmara Refrigerada destinado a Vigilância em\\n\\nSaúde. Data/Hora: 09 de outubro de 2020, as 08h30min. O edital do\\n\\nprocesso encontra-se a disposição dos interessados no site:\\n\\nhttp://transparencia.quebrangulo.al.gov.br/index.php/pt/, informações\\n\\nno email: cpl.quebrangulo@gmail.com.\\n\\n\\n\\nQuebrangulo, 25 de setembro de 2020.\\n\\n\\n\\nLUCIVAN ALEXANDRINO DE BARROS\\nPregoeiro.\\n\\nPublicado por:\\nLucivan Alexandrino de Barros\\n\\nCódigo Identificador:57DDFF11\\n\\n\\nCOMISSÃO PERMANENTE DE LICITAÇÃO\\n\\nAVISO DE LICITAÇÃO\\n\\n\\n\\nA PREFEITURA MUNICIPAL DE QUEBRANGULO torna público\\n\\naos interessados a realização da licitação na modalidade Pregão\\n\\nEletrônico de Nº 011/2020 - SRP, do tipo menor preço por item.\\n\\nObjeto: registro de preços para futuras e eventuais aquisições de\\n\\nequipamentos para formação de estúdio de gravação e edição de aulas\\n\\nonline. Data/Hora: 09 de outubro de 2020, às 10h30min. O edital do\\n\\nprocesso encontra-se a disposição dos interessados no site:\\n\\nhttp://transparencia.quebrangulo.al.gov.br/index.php/pt/, informações\\n\\nno email: cpl.quebrangulo@gmail.com.\\n\\n\\n\\nQuebrangulo, 25 de setembro de 2020.\\n\\n\\n\\nLUCIVAN ALEXANDRINO DE BARROS\\nPregoeiro.\\n\\nPublicado por:\\nLucivan Alexandrino de Barros\\n\\nCódigo Identificador:2859DF2A\\n\\n\\nCOMISSÃO PERMANENTE DE LICITAÇÃO\\n\\nAVISO DE CHAMADA PÚBLICA DE COMPRAS\\n\\n\\n\\nA PREFEITURA MUNICIPAL DE QUEBRANGULO torna público\\n\\naos interessados a realização da Chamada Pública de Compras Nº\\n\\n002/2020. Objeto: Aquisição de gêneros alimentícios da Agricultura\\n\\nFamiliar e do Empreendedor Familiar Rural, para o atendimento ao\\n\\nPrograma Nacional de Alimentação Escolar – PNAE. Data/Hora\\n\\nlimite para recebimento dos projetos de venda e documentos de\\n\\nhabilitação: 19 de outubro de 2020, as 12h00min. O edital do processo\\n\\nencontra-se a disposição dos interessados no site:\\n\\nhttp://transparencia.quebrangulo.al.gov.br/index.php/pt/, informações\\n\\nno email: cpl.quebrangulo@gmail.com.\\n\\n\\n\\nQuebrangulo, 25 de setembro de 2020.\\n\\n\\n\\nLUCIVAN ALEXANDRINO DE BARROS\\nPresidente CPL\\n\\nPublicado por:\\nLucivan Alexandrino de Barros\\n\\nCódigo Identificador:609BD443\\n\\n\\nCOMISSÃO PERMANENTE DE LICITAÇÃO\\n\\nEXTRATO DE APOSTILAMENTO DE CONTRATO\\n\\n\\n\\nContratante: MUNICÍPIO DE QUEBRANGULO, CNPJ n°\\n\\n12.241.675/0001-01. Contratadas: J M DELGADO JUNIOR,\\n\\nCNPJ/MF nº 00.818.307/0001-02. Objeto: contratação de empresa\\n\\npara Aquisição Parcelada de serviços de serigrafia. Com base no art.\\n\\n65 § 8º da Lei Federal nº 8.666/93, realiza-se o presente\\n\\nApostilamento, cujo objetivo é a inclusão da seguinte Dotação\\n\\nOrçamentária:\\n\\n\\n\\nUnidade: 60 – Secretaria Municipal de Educação e Cultura\\n\\nManutenção: 33.90.30, 33.90.39\\n\\nProjeto Atividade: 2006 – Manutenção da Secretaria de Educação –\\n\\nFonte: 0020 – MDE;\\n\\nUtilização da sede da Secretaria de Educação e Escolas.\\n\\nProjeto Atividade: 2017 – QSE – Fonte: 0020 - QSE;\\n\\nUtilização nas Escolas.\\n\\nProjeto Atividade: 2032 – Atividades Esportivas – Fonte: 0010 –\\n\\nRecursos Próprios;\\n\\nProjeto Atividade: 2033 – Apoio as Festividades / 2034 – Manutenção\\n\\nda Cultura – Fonte; 0010 – Recursos Próprios;\\n\\nUtilização nas sedes das Secretarias.\\n\\n\\n\\nQuebrangulo, 25 de setembro de 2020.\\n\\n\\n\\nMARCELO RICARDO VASCONCELOS LIMA\\nPrefeito\\n\\nPublicado por:\\nLucivan Alexandrino de Barros\\n\\nCódigo Identificador:F5C6E6FA\\n\\n\\nCOMISSÃO PERMANENTE DE LICITAÇÃO\\n\\nEXTRATO DE APOSTILAMENTO DE CONTRATO\\n\\n\\n\\nContratante: MUNICÍPIO DE QUEBRANGULO, CNPJ n°\\n\\n12.241.675/0001-01. Contratadas: MARIA ROSANGELA PEREIRA\\n\\nDA SILVA GALVÃO 04216748490 - MEI, CNPJ/MF sob nº\\n\\n32.234.727/0001-20. Objeto: contratação de empresa para\\n\\nfornecimento de peças novas originais e prestação de serviços de\\n\\nmanutenção preventiva e corretiva para os aparelhos de ar\\n\\ncondicionado da Prefeitura Municipal de Quebrangulo. Com base no\\n\\nart. 65 § 8º da Lei Federal nº 8.666/93, realiza-se o presente\\n\\nApostilamento, cujo objetivo é a inclusão da seguinte Dotação\\n\\nOrçamentária:\\n\\n\\n\\nUnidade: 60 – Secretaria Municipal de Educação e Cultura\\n\\nManutenção: 33.90.30, 33.90.39\\n\\nProjeto Atividade: 2006 – Manutenção da Secretaria de Educação –\\n\\nFonte: 0020 – MDE;\\n\\nUtilização da sede da Secretaria de Educação e Escolas.\\n\\nProjeto Atividade: 2017 – QSE – Fonte: 0020 QSE;\\n\\nUtilização nos equipamentos da Secretaria e Escolas.\\n\\nProjeto Atividade: 2026 – Ensino Infantil / 2027 – Ensino\\n\\nFundamental do Fundeb 40 – Fonte: 0030 – FUNDEB;\\n\\nUtilização nos equipamentos da Escola.\\n\\nProjeto Atividade: 2034 – Manutenção da Cultura – Fonte: 0010 –\\n\\nRECURSOS PRÓPRIOS;\\n\\nUtilização na sede da Secretaria.\\n\\n\\n\\nQuebrangulo, 25 de setembro de 2020.\\n\\n\\n\\nMARCELO RICARDO VASCONCELOS LIMA\\nPrefeito\\n\\nPublicado por:\\nLucivan Alexandrino de Barros\\n\\nCódigo Identificador:1388E7E7\\n\\n\\nCOMISSÃO PERMANENTE DE LICITAÇÃO\\n\\nEXTRATO DE APOSTILAMENTO DE CONTRATO\\n\\n\\n\\nContratante: MUNICÍPIO DE QUEBRANGULO, CNPJ n°\\n\\n12.241.675/0001-01. Contratada: A. A. EVANGELISTA DA SILVA\\n\\n- ME, CNPJ/MF sob nº 08.673.465/0001-15. Objeto: contratação de\\n\\nempresa para manutenção preventiva e corretiva de impressoras e\\n\\ncopiadoras com fornecimento de peças. Com base no art. 65 § 8º da\\n\\nLei Federal nº 8.666/93, realiza-se o presente Apostilamento, cujo\\n\\nobjetivo é a inclusão da seguinte Dotação Orçamentária:\\n\\n\\n\\nUnidade: 60 – Secretaria Municipal de Educação e Cultura\\n\\nManutenção: 33.90.30, 33.90.39\\n\\nProjeto Atividade: 2006 – Manutenção da Secretaria de Educação –\\n\\nFonte: 0020 – MDE;\\n\\nUtilização da sede da Secretaria de Educação e Escolas.\\n\\nProjeto Atividade: 2017 – QSE – Fonte: 0020 - QSE;\\n\\nUtilização nos equipamentos da Secretaria e Escolas.\\n\\n\\n\\n\\n\\n\\nwww.diariomunicipal.com.br/ama                                                                                        11\\n\\n\\n\\nProjeto Atividade: 2026 – Ensino Infantil / 2027 – Ensino\\n\\nFundamental do Fundeb 40 – Fonte: 0030 – FUNDEB;\\n\\nUtilização nos equipamentos da Escola.\\n\\n\\n\\nQuebrangulo, 25 de setembro de 2020.\\n\\n\\n\\nMARCELO RICARDO VASCONCELOS LIMA\\nPrefeito\\n\\nPublicado por:\\nLucivan Alexandrino de Barros\\n\\nCódigo Identificador:5F69E61A\\n\\n\\nCOMISSÃO PERMANENTE DE LICITAÇÃO\\n\\nEXTRATO DE TERMO ADITIVO DE CONTRATO\\n\\n\\n\\nContratante: MUNICÍPIO DE QUEBRANGULO, CNPJ n°\\n\\n12.241.675/0001-01. Contratada: KV LOCAÇÕES E SERVIÇOS\\n\\nEIRELI, CNPJ n.º 27.104.634/0001-40. Objeto: Prorrogação da\\n\\nVigência. Fica prorrogada a vigência do Contrato 178/2019, que tem\\n\\ncomo objeto implantação de melhorias habitacionais para o controle\\n\\nda doença de chagas no município de Quebrangulo, até 03 de junho de\\n\\n2021.\\n\\nQuebrangulo, 11 de maio de 2020.\\n\\n\\n\\nMARCELO RICARDO VASCONCELOS LIMA\\nPrefeito\\n\\nPublicado por:\\nLucivan Alexandrino de Barros\\n\\nCódigo Identificador:F2B590A3\\n\\n\\nCOMISSÃO PERMANENTE DE LICITAÇÃO\\n\\nEXTRATO DE TERMO ADITIVO DE CONTRATO\\n\\n\\n\\nContratante: MUNICÍPIO DE QUEBRANGULO, CNPJ n°\\n\\n12.241.675/0001-01. Contratada: CONSTRUTORA TAMBAU\\n\\nLTDA, CNPJ n.º 10.578.355/0001-16. Objeto: Prorrogação da\\n\\nVigência. Fica prorrogada a vigência do Contrato 309/2019, que tem\\n\\ncomo objeto a construção das instalações do centro de referência\\n\\nespecializada de assistência social – CREAS, até 10 de setembro de\\n\\n2021.\\n\\n\\n\\nquebrangulo, 13 de agosto de 2020.\\n\\n\\n\\nMARCELO RICARDO VASCONCELOS LIMA\\nPrefeito\\n\\nPublicado por:\\nLucivan Alexandrino de Barros\\n\\nCódigo Identificador:F59A96CB\",\n  \"data_publicacao\": \"2020-09-28\"\n}",
  "{\n  \"municipio\": \"RIO LARGO\",\n  \"id\": \"rio-largo\",\n  \"cabecalho\": \"Alagoas , 28 de Setembro de 2020   •   Diário Oficial dos Municípios do Estado de Alagoas   •    ANO VIII | Nº 1382 \",\n  \"texto\": \"Alagoas , 28 de Setembro de 2020   •   Diário Oficial dos Municípios do Estado de Alagoas   •    ANO VIII | Nº 1382 \\n\\nESTADO DE ALAGOAS\\n\\nPREFEITURA MUNICIPAL DE RIO LARGO\\n\\n\\n\\nSECRETARIA MUNICIPAL DE ADMINISTRAÇÃO E\\n\\nRECURSOS HUMANOS\\n\\nEXTRATO DO CONTRATO Nº 60/2020\\n\\n\\n\\nEXTRATO DO CONTRATO Nº 60/2020\\n\\nCONTRATANTE: O MUNICÍPIO DE RIO LARGO/AL, CNPJ sob\\n\\nnº 12.200.168/0001-20.\\n\\nCONTRATADO: NP CAPACITAÇÃO E SOLUÇÕES\\n\\nTECNOLÓGICAS LTDA, CNPJ Nº 07.797.967/0001-95.\\n\\nOBJETO: Contratação de empresa especializada em pesquisa de\\n\\nmercado, através de Banco de Preços, destinado a ofertar maior\\n\\nfluidez aos processos de aquisição da Prefeitura Municipal de Rio\\n\\nLargo/AL.\\n\\nDA VIGÊNCIA: O contrato terá vigência pelo prazo de 12(doze)\\n\\nvezes, iniciado após a assinatura, sendo vedada a sua prorrogação para\\n\\nalém do referido período.\\n\\nDO VALOR TOTAL DO CONTRATO: R$ 8.975,00 (Oito mil,\\n\\nnovecentos e setenta e cinco reais).\\n\\nSIGNATÁRIOS: Gilberto Gonçalves da Silva, pelo\\n\\nCONTRATANTE; e Rudimar Barbosa dos Reis, pela\\n\\nCONTRATADA.\\n\\n\\n\\nPublicado por:\\nPâmela Correia Moura\\n\\nCódigo Identificador:B120F7E6\\n\\n\\nSECRETARIA MUNICIPAL DE DESENVOLVIMENTO\\n\\nSOCIAL E HABITAÇÃO\\n\\nTERMO DE RATIFICAÇÃO DE DISPENSA DE LICITAÇÃO\\n\\n\\n\\nTERMO DE RATIFICAÇÃO DE DISPENSA DE LICITAÇÃO\\n\\nProcesso nº: 0828-001/2020\\n\\nInteressado(a): SECRETARIA MUNICIPAL DE ASSISTÊNCIA\\n\\nSOCIAL.\\n\\nAssunto: AQUISIÇÃO DE MATERIAIS NECESSÁRIOS NO\\n\\nCOMBATE AO COVID-19.\\n\\n\\nCom base no artigo 4°, da Lei Federal n.º 13.979 de 2020, e de acordo\\n\\ncom os termos das peças que compõem o processo administrativo,\\n\\nobservada todas as normas disciplinadoras e princípios\\n\\nadministrativos, RECONHEÇO a situação de dispensa de licitação,\\n\\nobjetivando a contratação de empresa para o fornecimento de\\n\\nMaterial Necessário ao combate a COVID-19, a ser firmada com a\\n\\nempresa UP DISTRIBUIDORA DE PRODUTOS\\n\\nDESCARTÁVEIS LTDA, inscrita no CNPJ sob n.º\\n\\n12.423.997/0001-71, no valor total de R$ 9.906,80 (Nove mil,\\n\\nnovecentos e seis reais e oitenta centavos).\\n\\n\\n\\nRio Largo/Al, 25 de Setembro de 2020.\\n\\n\\n\\nGILBERTO GONÇALVES DA SILVA\\nPrefeito\\n\\nPublicado por:\\nPâmela Correia Moura\\n\\nCódigo Identificador:E26C582C\\n\\n\\nSECRETARIA MUNICIPAL DE EDUCAÇÃO\\n\\nEXTRATO DO CONTRATO Nº 57/2020\\n\\n\\n\\nEXTRATO DO CONTRATO Nº 57/2020\\n\\nCONTRATANTE: O MUNICÍPIO DE RIO LARGO/AL, CNPJ sob\\n\\nnº 12.200.168/0001-20.\\n\\nCONTRATADO: COMERCIAL GETRIX EIRELI, CNPJ Nº\\n\\n03.488.409/0001-97.\\n\\nOBJETO: Aquisição de caminhas empilháveis e lenços umedecidos\\n\\npara atender as necessidades da Secretaria Municipal de Educação do\\n\\nMunicípio de Rio Largo/AL.\\n\\nDA VIGÊNCIA: 31 de dezembro do corrente ano, contados da data\\n\\nde publicação do extrato contratual.\\n\\nData de assinatura: 25 de Setembro de 2020.\\n\\nDO VALOR TOTAL DO CONTRATO: R$ 54.328,76 (Cinquenta e\\n\\nquatro mil, trezentos e vinte e oito reais e setenta e seis centavos).\\n\\nSIGNATÁRIOS: Gilberto Gonçalves da Silva, pelo\\n\\nCONTRATANTE; e Miguel Garde Filho, pela CONTRATADA.\\n\\n\\n\\nPublicado por:\\nPâmela Correia Moura\\n\\nCódigo Identificador:789FE5D2\",\n  \"data_publicacao\": \"2020-09-28\"\n}",
  "{\n  \"municipio\": \"SANTA LUZIA DO NORTE\",\n  \"id\": \"santa-luzia-do-norte\",\n  \"cabecalho\": \"Alagoas , 28 de Setembro de 2020   •   Diário Oficial dos Municípios do Estado de Alagoas   •    ANO VIII | Nº 1382 \",\n  \"texto\": \"Alagoas , 28 de Setembro de 2020   •   Diário Oficial dos Municípios do Estado de Alagoas   •    ANO VIII | Nº 1382 \\n\\nESTADO DE ALAGOAS\\n\\nPREFEITURA MUNICIPAL DE SANTA LUZIA DO NORTE\\n\\n\\n\\nGABINETE PREFEITO\\n\\nEXTRATO DA ATA DE REGISTRO DE PREÇOS Nº 05/2020\\n\\n\\n\\nEXTRATO DA ATA DE REGISTRO DE PREÇOS Nº 05/2020\\n\\n\\nPregão Eletrônico nº05/2020.\\nFundamento Legal: Lei Federal nº 10.520/2002 Decreto Federal\\n\\n7.892/2013, Decreto Federal 10.024/2019 e Lei Federal nº 8.666/93 e\\n\\nsuas alterações posteriores;\\n\\n\\n\\nÓrgão Gerenciador: PREFEITURA MUNICIPAL DE SANTA\\n\\nLUZIA DO NORTE/AL;\\n\\n\\n\\nFornecedora Registrada:\\n\\n\\n\\n\\n\\n\\nwww.diariomunicipal.com.br/ama                                                                                        12\\n\\n\\n\\nDetentora: C DE A FERREIRA E CIA LTDA, CNPJ:\\n\\n33.330.526/0001-99, valor registrado R$ 31.790,00 (trinta e um mil,\\n\\nsetecentos e noventa reais);\\n\\nObjeto: REGISTRO DE PREÇOS PARA FUTURA E\\n\\nEVENTUAL CONTRATAÇÃO DE EMPRESA PARA\\n\\nAQUISIÇÃO DE RESMAS DE PAPEL A4, destinados à\\n\\nmanutenção das atividades das Secretarias do Município de Santa\\n\\nLuzia do Norte/AL.\\n\\nVigência: 12 (doze) meses.\\n\\nFirmado em: 15/09/2020.\\n\\nSignatários: Márcio Augusto Araújo Lima e Celma de Albuquerque\\n\\nFerreira.\\n\\nPublicado por:\\nGivanilda Maria Nascimento Araujo\\n\\nCódigo Identificador:D2F402EF\",\n  \"data_publicacao\": \"2020-09-28\"\n}",
  "{\n  \"municipio\": \"SANTANA DO IPANEMA\",\n  \"id\": \"santana-do-ipanema\",\n  \"cabecalho\": \"Alagoas , 28 de Setembro de 2020   •   Diário Oficial dos Municípios do Estado de Alagoas   •    ANO VIII | Nº 1382 \",\n  \"texto\": \"Alagoas , 28 de Setembro de 2020   •   Diário Oficial dos Municípios do Estado de Alagoas   •    ANO VIII | Nº 1382 \\n\\nESTADO DE ALAGOAS\\n\\nPREFEITURA MUNICIPAL DE SANTANA DO IPANEMA\\n\\n\\n\\nGABINETE DO PREFEITO\\n\\nAVISO DE HOMOLOGAÇÃO\\n\\n\\n\\nProcesso nº 03.24.098/2020\\n\\nPregão Eletrônico nº 14/2020-SRP\\n\\nFace ao constante nos autos do procedimento licitatório Pregão\\n\\nEletrônico nº 14/2020-SRP, do Tipo Menor Preço, referente ao\\n\\nProcesso 03.24.098/2020, HOMOLOGO, com fundamento no Artigo\\n\\n4º, Inciso XXII, da Lei Federal nº 10.520/2002, a presente licitação\\n\\npara que a Adjudicação nela contida produza seus efeitos jurídicos e\\n\\nlegais.\\n\\n\\n\\nCHRISTIANE BULHÕES BARROS MELO SILVA\\nPrefeita em Exercício\\n\\nPublicado por:\\nIsadora Almeida Melo\\n\\nCódigo Identificador:20F97BCA\\n\\n\\nGABINETE DO PREFEITO\\n\\nAVISO DE HOMOLOGAÇÃO\\n\\n\\n\\nProcesso nº 05.12.013/2020\\n\\nPregão Eletrônico nº 16/2020-SRP\\n\\nFace ao constante nos autos do procedimento licitatório Pregão\\n\\nEletrônico nº 16/2020-SRP, do Tipo Menor Preço, referente ao\\n\\nProcesso nº 05.12.013/2020, HOMOLOGO, com fundamento no\\n\\nArtigo 4º, Inciso XXII, da Lei Federal nº 10.520/2002, a presente\\n\\nlicitação para que a Adjudicação nela contida produza seus efeitos\\n\\njurídicos e legais.\\n\\n\\n\\nCHRISTIANE BULHÕES BARROS MELO SILVA\\nPrefeita em Exercício\\n\\nPublicado por:\\nIsadora Almeida Melo\\n\\nCódigo Identificador:2DF25421\\n\\n\\nGABINETE DO PREFEITO\\n\\nAVISO DE HOMOLOGAÇÃO\\n\\n\\n\\nProcesso nº 05.25.015/2020\\n\\nPregão Eletrônico nº 17/2020-SRP\\n\\nFace ao constante nos autos do procedimento licitatório Pregão\\n\\nEletrônico nº 17/2020-SRP, do Tipo Menor Preço, referente ao\\n\\nProcesso nº 05.25.015/2020, HOMOLOGO, com fundamento no\\n\\nArtigo 4º, Inciso XXII, da Lei Federal nº 10.520/2002, a presente\\n\\nlicitação para que a Adjudicação nela contida produza seus efeitos\\n\\njurídicos e legais.\\n\\n\\n\\nCHRISTIANE BULHÕES BARROS MELO SILVA\\nPrefeita em Exercício\\n\\nPublicado por:\\nIsadora Almeida Melo\\n\\nCódigo Identificador:5AC4F2AE\\n\\n\\n\\nGABINETE DO PREFEITO\\n\\nAVISO DE HOMOLOGAÇÃO\\n\\n\\n\\nProcesso nº 04.22.026/2020\\n\\nPregão Eletrônico nº 18/2020\\n\\nFace ao constante nos autos do procedimento licitatório Pregão\\n\\nEletrônico nº 18/2020, do Tipo Menor Preço, referente ao Processo nº\\n\\n04.22.026/2020, HOMOLOGO, com fundamento no Artigo 4º, Inciso\\n\\nXXII, da Lei Federal nº 10.520/2002, a presente licitação para que a\\n\\nAdjudicação nela contida produza seus efeitos jurídicos e legais.\\n\\n\\n\\nCHRISTIANE BULHÕES BARROS MELO SILVA\\nPrefeita\\n\\nPublicado por:\\nIsadora Almeida Melo\\n\\nCódigo Identificador:81F5D5E0\\n\\n\\nGABINETE DO PREFEITO\\n\\nDECRETO Nº 121 DE 21 DE AGOSTO DE 2020*\\n\\n\\n\\n“Disciplina o procedimento relativo ao repasse do\\n\\nproduto de arrecadação da Contribuição para o\\n\\nCusteio da Iluminação Pública – CIP instituída na\\n\\nLei Municipal nº 1.019/2017, em decorrência da Res.\\n\\nnº 888, de 30 de junho de 2020, da ANEEL, que\\n\\nalterou o Res. nº 414/2010 e dá outras\\n\\nprovidências.”\\n\\n\\n\\nA Prefeita do Município de Santana do Ipanema, deste Estado de\\n\\nAlagoas, no uso de suas atribuições legais, que lhe confere os arts. 30,\\n\\nI, II e III e 149-A da CRFB/88, a Lei Orgânica do Município, o art.\\n\\n165 do Código Tributário Nacional (CTN), considerando a\\n\\nnecessidade de disciplinar o procedimento administrativo referente ao\\n\\nrepasse do produto de arrecadação da Contribuição para o Custeio da\\n\\nIluminação Pública - CIP e,\\n\\n\\n\\nConsiderando a necessidade de Regulamentação da Lei Municipal nº\\n\\n1.019, de 29 de setembro de 2017;\\n\\n\\n\\nConsiderando, também, a necessidade de adequar o mencionado\\n\\nprocedimento às disposições da Res. nº 888, de 30 de junho de 2020,\\n\\nda ANEEL que alterou a Resolução nº 414, de 2010;\\n\\n\\n\\nConsiderando, ainda, a importância do mencionado tributo para o\\n\\nMunicípio, principalmente para melhoria do parque de iluminação\\n\\npública e por consequência da segurança pública,\\n\\n\\n\\nConsiderando a obrigação de a Distribuidora de Energia Elétrica\\n\\ncobrar a CIP na fatura de energia elétrica;\\n\\n\\n\\nD E C R E T A:\\n\\n\\nArt. 1º Este Decreto regulamenta a Lei Municipal n. 1.019, de 29 de\\n\\nsetembro de 2017.\\n\\n\\n\\n§1º O repasse dos valores da contribuição para o custeio do serviço de\\n\\niluminação pública deverá ocorrer até o décimo dia útil do mês\\n\\nsubsequente ao de arrecadação para as contas correntes indicadas pelo\\n\\nConsórcio Público para Gestão de Energia Elétrica e Serviços\\n\\nPúblicos – CIGIP.\\n\\n\\n\\n§2º Fica indicado o CIGIP, personalidade jurídica de natureza\\n\\nAutárquica, como gestor do produto de arrecadação da CIP.\\n\\n\\n\\n§3º A não observância do §1º implica a cobrança de multa de 2%\\n\\n(dois por cento), atualização monetária e juros de mora previstos no\\n\\nart. 126 da Resolução Nº 414/2010 da Aneel, salvo disposição diversa\\n\\nem lei ordinária municipal.\\n\\n\\n\\n§4º É vedado a realização da compensação dos valores arrecadados da\\n\\ncontribuição com os créditos devidos pelo poder público municipal ou\\n\\ndistrital.\\n\\n\\n\\n\\n\\n\\n\\n\\nwww.diariomunicipal.com.br/ama                                                                                        13\\n\\n\\n\\nArt. 2º A distribuidora deve fornecer, no prazo de até 30 (trinta) dias\\n\\ndo faturamento ao CIGIP, as informações necessárias para\\n\\noperacionalização da cobrança da contribuição para o custeio do\\n\\nserviço de iluminação pública na fatura de energia e gestão tributária.\\n\\n\\n\\nArt. 3º Deve ser celebrado um novo contrato do serviço de\\n\\ndistribuição de energia elétrica pelo Poder Público Municipal para o\\n\\nserviço de iluminação pública com a distribuidora de energia elétrica\\n\\ndo Estado de Alagoas, e que deve observar o descrito na Lei n.º\\n\\n8.666/93 e em conformidade com os arts. 60 e seguintes da Resolução\\n\\nnormativa da ANEEL n.º 414/2010.\\n\\n\\n\\nArt. 3º Este Decreto entra em vigor na data de sua publicação,\\n\\nrevogadas as disposições em contrário.\\n\\n\\n\\nDê-se Ciência, Publique-se, Registre-se e Cumpra-se.\\n\\n\\n\\nPrefeitura Municipal de Santana do Ipanema/AL, 21 de agosto de\\n\\n2020.\\n\\n\\n\\nCHRISTIANE BULHÕES BARROS MELO SILVA\\nPrefeita Municipal\\n\\n\\n\\nO presente Decreto foi registrado na Secretaria Municipal de Gestão\\n\\nde Pessoas, Logística e Patrimônio e publicado no Diário Oficial dos\\n\\nMunicípios de Alagoas (Lei Municipal n.º 1040/2019), em 21 de\\n\\nagosto de 2020.\\n\\n\\n\\nANTÔNIO DE PÁDUA NUNES BATISTA\\nSecretário Municipal de Gestão de Pessoas, Logística e Patrimônio.\\n\\n\\n\\n*Republicado por Incorreção\\n\\nPublicado por:\\nVanessa Silva de Oliveira\\n\\nCódigo Identificador:296D1662\\n\\n\\nSECRETARIA MUNICIPAL DE GESTÃO DE PESSOAS,\\n\\nLOGÍSTICA E PATRIMÔNIO\\n\\nEXTRATO DE ATA DE REGISTRO DE PREÇOS\\n\\n\\n\\nAta de Registro de Preços nº PE14/2020-SRP – Processo nº\\n\\n03.24.098/2020 – Pregão Eletrônico nº 14/2020-SRP –\\n\\nFundamentação Legal: Lei Federal nº 10.520/2002, Lei Federal nº\\n\\n8.666/93 e Decretos Municipais nº 28/2017 e nº 20/2020 – Fornecedor\\n\\nRegistrado: PV PNEUS EIRELI – ME (CNPJ Nº 21.848.971/0001-\\n\\n66) – Objeto: Registro de preços para aquisição de pneus e diversos\\n\\n(LOTES 01, 03, 04, 05, 06, 07, 08, 09, 10, 11, 12, 13, 15, 16, 17, 18,\\n\\n19, 20, 21, 22, 23, 24, 28, 29, 31, 32 e 33) – Valor global: R$\\n\\n600.202,50 (seiscentos mil duzentos e dois reais e cinquenta centavos)\\n\\n– Vigência: 12 (doze) meses.\\n\\nPublicado por:\\nIsadora Almeida Melo\\n\\nCódigo Identificador:922EA05A\\n\\n\\nSECRETARIA MUNICIPAL DE GESTÃO DE PESSOAS,\\n\\nLOGÍSTICA E PATRIMÔNIO\\n\\nEXTRATO DE ATA DE REGISTRO DE PREÇOS\\n\\n\\n\\nAta de Registro de Preços nº PE16/2020-SRP – Processo nº\\n\\n05.12.013/2020– Pregão Eletrônico nº 16/2020-SRP – Fundamentação\\n\\nLegal: Lei Federal nº 10.520/2002, Lei Federal nº 8.666/93 e Decretos\\n\\nMunicipais nº 28/2017 e nº 20/2020 – Fornecedor Registrado:\\n\\nNORDESTE DISTRIBUIDORA DE ALIMENTOS LTDA (CNPJ Nº\\n\\n08.042.394/0001-52) – Objeto: Registro de preços para aquisição de\\n\\nkits para merenda escolar - (LOTES 01 – KIT I – CRECHE E PRÉ-\\n\\nESCOLA (COTA PRINCIPAL), LOTE 02 – KIT I – CRECHE E\\n\\nPRÉ-ESCOLA (COTA RESERVADA DO LOTE 01, LEI 123/06);\\n\\nLOTE 03 – KIT II – ENSINO FUNDAMENTAL I (COTA\\n\\nPRINCIPAL); LOTE 04 – KIT II – ENSINO FUNDAMENTAL I\\n\\n(COTA RESERVADA DO LOTE 03, LEI 123/06); LOTE 05 – KIT\\n\\nIII – ENSINO FUNDAMENTAL II E EJA (COTA PRINCIPAL) E\\n\\nLOTE 06 – KIT III – ENSINO FUNDAMENTAL II E EJA (COTA\\n\\nRESERVADA DO LOTE 05, ELI 123/06)) – Valor global: R$\\n\\n1.826.340,00 (um milhão oitocentos e vinte e seis mil trezentos e\\n\\nquarenta reais) – Vigência: 12 (doze) meses.\\n\\nPublicado por:\\nIsadora Almeida Melo\\n\\nCódigo Identificador:C20E1EF5\\n\\n\\nSECRETARIA MUNICIPAL DE GESTÃO DE PESSOAS,\\n\\nLOGÍSTICA E PATRIMÔNIO\\n\\nEXTRATO DE ATA DE REGISTRO DE PREÇOS\\n\\n\\n\\nAta de Registro de Preços nº PE17/2020-SRP – Processo nº\\n\\n05.25.015/2020– Pregão Eletrônico nº 17/2020-SRP – Fundamentação\\n\\nLegal: Lei Federal nº 10.520/2002, Lei Federal nº 8.666/93 e Decretos\\n\\nMunicipais nº 28/2017 e nº 20/2020 – Fornecedor Registrado: R & B\\n\\nLABORATORIO PROTETICO LTDA (CNPJ 17.391.173/0001-80) –\\n\\nObjeto: Registro de preços para Contratação de Serviços de\\n\\nConfecção de Próteses Dentárias - (LOTE 01 - PRÓTESES\\n\\nDENTÁRIAS) – Valor global: R$ 78.246,00 (setenta e oito mil\\n\\nduzentos e quarenta e seis reais) – Vigência: 12 (doze) meses.\\n\\n\\n\\nPublicado por:\\nIsadora Almeida Melo\\n\\nCódigo Identificador:E4872251\\n\\n\\nSECRETARIA MUNICIPAL DE GESTÃO DE PESSOAS,\\n\\nLOGÍSTICA E PATRIMÔNIO\\n\\nEXTRATO DE CONTRATO\\n\\n\\n\\nContrato nº PE18/2020 – Processo nº 04.22.026/2020 – Pregão\\n\\nEletrônico nº 18/2020 – Fundamentação Legal: Lei Federal nº\\n\\n10.520/2002, Lei Federal nº 8.666/93 e Decretos Municipais nº\\n\\n28/2017 e nº 20/2020 – Fornecedor Registrado: BIOSYSTEMSNE\\n\\nCOMERCIO DE PROD LAB E HOSP LTDA (CNPJ nº\\n\\n08.282.077/0001-03) – Objeto: serviços continuados de Locação de\\n\\nMáquinas de análise Hematológica e Bioquímica automatizadas\\n\\ndestinadas para o Laboratório de Análises Clínicas municipal (LOTES\\n\\n01 e 02) – Valor global: R$ 97.200,00 (noventa e sete mil duzentos) –\\n\\nVigência: até 31 de dezembro de 2020.\\n\\nPublicado por:\\nIsadora Almeida Melo\\n\\nCódigo Identificador:434FE834\",\n  \"data_publicacao\": \"2020-09-28\"\n}",
  "{\n  \"municipio\": \"SANTANA DO MUNDAÚ\",\n  \"id\": \"santana-do-mundau\",\n  \"cabecalho\": \"Alagoas , 28 de Setembro de 2020   •   Diário Oficial dos Municípios do Estado de Alagoas   •    ANO VIII | Nº 1382 \",\n  \"texto\": \"Alagoas , 28 de Setembro de 2020   •   Diário Oficial dos Municípios do Estado de Alagoas   •    ANO VIII | Nº 1382 \\n\\nESTADO DE ALAGOAS\\n\\nPREFEITURA MUNICIPAL DE SANTANA DO MUNDAÚ\\n\\n\\n\\nGABINETE DO PREFEITO\\n\\nAVISO DE HOMOLOGAÇÃO PREGÃO ELETRÔNICO Nº\\n\\n007/2020\\n\\n\\n\\nDe posse dos documentos que compõem o processo licitatório de n.º\\n\\n2020.0603.0004.01 realizado na modalidade Pregão Eletrônico n.º\\n\\n007/2020, cujo objeto é a aquisição de pneus e câmaras de ar\\n\\ndestinados à frota de veículos das Secretarias Municipais de Santana\\n\\ndo Mundaú, conforme ata de sessão pública, datada de 22 de setembro\\n\\nde 2020.\\n\\nConsiderando o teor do Parecer da Procuradoria Municipal desta\\n\\nPrefeitura; Considerando a adjudicação proferida pelo Senhor\\n\\nPregoeiro, referente ao pregão eletrônico nº 007/2020, e;\\n\\nConsiderando a inexistência de qualquer vício ou irregularidade,\\n\\nRESOLVE:\\n\\n\\n\\nI – HOMOLOGAR a adjudicação proferida pelo Pregoeiro, referente\\n\\nà licitação na modalidade Pregão Eletrônico, sob o n.º 007/2020 –\\n\\nProcesso 2020.0603.0004.01, para aquisição de pneus e câmaras de ar\\n\\ndestinados à frota de veículos das Secretarias Municipais de Santana\\n\\ndo Mundaú/AL, pelo melhor lance ofertado dos itens, às empresas a\\n\\nseguir vencedoras: LASER PEÇAS E MANUTENÇÃO\\n\\nAUTOMOTIVA LTDA, inscrita no CNPJ sob o n.º 01.774.047/0001-\\n\\n75, MARY SOARES & ALTAIR AUTOPEÇAS E PNEUS LTDA,\\n\\ninscrita no CNPJ sob o n.º 28.923.890/0001-22, CONSTANTINO\\n\\nPNEUS EIRELI, inscrita no CNPJ sob o n.º 35.793.795/0001-17 e\\n\\nEVOKS COMÉRCIO IMPORTAÇÃO E EXPORTAÇÃO LTDA,\\n\\ninscrita no CNPJ sob o n.º 37.790.246/0001-14, no valor máximo do\\n\\n\\n\\n\\n\\n\\nwww.diariomunicipal.com.br/ama                                                                                        14\\n\\n\\n\\nreferido Pregão é de R$ 529.662,47 (quinhentos e vinte e nove mil,\\n\\nseiscentos e sessenta e dois reais e quarenta e sete centavos).\\n\\n\\n\\nII – PUBLIQUE-SE a presente homologação na forma da Lei para\\n\\nfins de eficácia.\\n\\n\\n\\nSantana do Mundaú, 25 de setembro de 2020.\\n\\n\\n\\nARTHUR DA PURIFICAÇÃO FREITAS LOPES\\nPrefeito\\n\\nPublicado por:\\nThiago de Farias Cunha Seixas\\n\\nCódigo Identificador:60ABD58A\\n\\n\\nGABINETE DO PREFEITO\\n\\nTERMO DE RATIFICAÇÃO DE DISPENSA DE LICITAÇÃO\\n\\n\\n\\nConsiderando as informações constantes nos despachos, documentos e\\n\\nparecer contidos nos autos do processo em epígrafe, RATIFICO a\\n\\ndispensa de licitação reconhecida pela Procuradoria desta Prefeitura\\n\\npara contratar a empresa MED FARMACE DISTRIBUIDORA DE\\n\\nMEDICAMENTOS LTDA EPP, inscrita no CNPJ sob o nº\\n\\n69.950.913/0001-75, visando a aquisição de medicamentos de uso\\n\\ncontínuo para atender as necessidades de reabastecimento das\\n\\nUnidades Básica de Saúde do município de Santana do Mundaú/AL.\\n\\nEssa ratificação se fundamenta no art. 24, II da Lei Federal nº\\n\\n8.666/1993. O valor global da aquisição é de R$ 14.600,00 (quatorze\\n\\nmil e seiscentos reais).\\n\\n\\n\\nSantana do Mundaú, 25 de setembro de 2020.\\n\\n\\n\\nARTHUR DA PURIFICAÇÃO FREITAS LOPES\\nPrefeito\\n\\nPublicado por:\\nThiago de Farias Cunha Seixas\\n\\nCódigo Identificador:897D7B15\\n\\n\\nGABINETE DO PREFEITO\\n\\nTERMO DE RATIFICAÇÃO DE DISPENSA DE LICITAÇÃO\\n\\n\\n\\nConsiderando as informações constantes nos despachos, documentos e\\n\\nparecer contidos nos autos do processo em epígrafe, RATIFICO a\\n\\ndispensa de licitação reconhecida pela Procuradoria desta Prefeitura\\n\\npara contratar a empresa CENUTRI – CENTRO ESPECIALIZADO\\n\\nDE NUTRIÇÃO LTDA, inscrita no CNPJ sob o nº 11.705.404/0001-\\n\\n05, visando a aquisição de suplemento alimentar para atender as\\n\\nnecessidades de reabastecimento das Unidades Básica de Saúde do\\n\\nmunicípio de Santana do Mundaú/AL. Essa ratificação se fundamenta\\n\\nno art. 24, II da Lei Federal nº 8.666/1993. O valor global da\\n\\naquisição é de R$ 3.982,50 (três mil, novecentos e oitenta e dois reais\\n\\ne cinquenta centavos).\\n\\n\\n\\nSantana do Mundaú, 25 de setembro de 2020.\\n\\n\\n\\nARTHUR DA PURIFICAÇÃO FREITAS LOPES\\nPrefeito\\n\\nPublicado por:\\nThiago de Farias Cunha Seixas\\n\\nCódigo Identificador:5F40438D\",\n  \"data_publicacao\": \"2020-09-28\"\n}",
  "{\n  \"municipio\": \"SENADOR RUI PALMEIRA\",\n  \"id\": \"senador-rui-palmeira\",\n  \"cabecalho\": \"Alagoas , 28 de Setembro de 2020   •   Diário Oficial dos Municípios do Estado de Alagoas   •    ANO VIII | Nº 1382 \",\n  \"texto\": \"Alagoas , 28 de Setembro de 2020   •   Diário Oficial dos Municípios do Estado de Alagoas   •    ANO VIII | Nº 1382 \\n\\nESTADO DE ALAGOAS\\n\\nPREFEITURA MUNICIPAL DE SENADOR RUI PALMEIRA\\n\\n\\n\\nGABINETE DA PREFEITA\\n\\nAVISO DE LICITAÇÃO\\n\\n\\n\\nAviso de Licitação – Tomada de Preços Nº 07/2020\\n\\nProcesso: 0914004/2020. Objeto: Contratação de empresa de\\n\\nengenharia para execução das obras e serviços de recuperação de uma\\n\\npassagem molhada, localizada na Rua Boa Vista e recuperação de\\n\\numa quadra poliesportiva, localizada na comunidade de Cabeça do\\n\\nBoi, ambas no Município de Senador Rui Palmeira - AL. Modalidade:\\n\\nTomada de Preços. Tipo: Menor Preço, representado pelo menor\\n\\npreço por lote. Data e horário da abertura da sessão pública:\\n\\n14/10/2020 – 9 h. (horário de Brasília). Endereço: Comissão\\n\\nPermanente de Licitação, localizada na Rua Santa Terezinha, nº 19 -\\n\\nCentro – Senador Rui Palmeira - AL. Endereço Eletrônico:\\n\\nsetorlicitacoessrp@hotmail.com. Horário para entrega do edital: De 8\\n\\nàs 12 horas.\\n\\n\\n\\nSenador Rui Palmeira - AL, 25 de setembro de 2020.\\n\\n\\n\\nROGÉRIO VIEIRA CABRAL\\nPresidente CPL.\\n\\nPublicado por:\\nJaime Aureo Nunes\\n\\nCódigo Identificador:0A975E15\",\n  \"data_publicacao\": \"2020-09-28\"\n}",
  "{\n  \"municipio\": \"TEOTONIO VILELA\",\n  \"id\": \"teotonio-vilela\",\n  \"cabecalho\": \"Alagoas , 28 de Setembro de 2020   •   Diário Oficial dos Municípios do Estado de Alagoas   •    ANO VIII | Nº 1382 \",\n  \"texto\": \"Alagoas , 28 de Setembro de 2020   •   Diário Oficial dos Municípios do Estado de Alagoas   •    ANO VIII | Nº 1382 \\n\\nESTADO DE ALAGOAS\\n\\nPREFEITURA MUNICIPAL DE TEOTONIO VILELA\\n\\n\\n\\nSECRETARIA MUNICIPAL DE FINANÇAS E\\n\\nPLANEJAMENTO\\n\\nAVISO DE LICITAÇÃO - PREGÃO ELETRÔNICO N°\\n\\n034/2020 (LICITAÇÃO Nº 836337)\\n\\n\\n\\nPREGÃO ELETRÔNICO N° 034/2020 (Licitação nº 836337) –\\n\\nTIPO MENOR PREÇO POR LOTE – OBJETO: Locação de\\n\\nMáquinas. Data da Disputa 09 de outubro de 2020, as 08h30min.\\n\\nAcolhimento das propostas a partir de 28/09/2020 às 08h até as\\n\\n08h30min do dia 09 de outubro de 2020, horário de Brasília. No site:\\n\\nwww.licitacoes-e.com.br.\\n\\n\\n\\nMais informações poderão ser obtidas no setor de licitações localizado\\n\\nna Rua Firmina Pacheco, 60, Centro, Teotônio Vilela/AL, no horário\\n\\nde 08:00 a 12:00 horas e através do site www.teotoniovilela.al.gov.br.\\n\\nTelefone para contato (82) 3543 – 1301. Esclarecimentos e\\n\\nimpugnações para o e-mail: pregaopmtv@gmail.com.\\n\\n\\n\\nTeotônio Vilela/AL, 25 de setembro de 2020.\\n\\n\\n\\nRICARDO LIMA TORRES\\nPregoeiro\\n\\nPublicado por:\\nEveraldo da Silva Oliveira Junior\\n\\nCódigo Identificador:75FABEB5\\n\\n\\nSECRETARIA MUNICIPAL DE FINANÇAS E\\n\\nPLANEJAMENTO\\n\\nAVISO DE LICITAÇÃO - PREGÃO ELETRÔNICO N°\\n\\n035/2020 (LICITAÇÃO Nº 821187)\\n\\n\\n\\nPREGÃO ELETRÔNICO N° 035/2020 (Licitação nº 821187) –\\n\\nTIPO MENOR PREÇO POR LOTE – OBJETO: Aquisição de\\n\\nLixeiras Papeleiras. Data da Disputa 09 de outubro de 2020, as\\n\\n14h00min. Acolhimento das propostas a partir de 28/09/2020 às 08h\\n\\naté as 14h00min do dia 09 de outubro de 2020, horário de Brasília. No\\n\\nsite: www.licitacoes-e.com.br.\\n\\n\\n\\nMais informações poderão ser obtidas no setor de licitações localizado\\n\\nna Rua Firmina Pacheco, 60, Centro, Teotônio Vilela/AL, no horário\\n\\nde 08:00 a 12:00 horas e através do site www.teotoniovilela.al.gov.br.\\n\\nTelefone para contato (82) 3543 – 1301. Esclarecimentos e\\n\\nimpugnações para o e-mail: pregaopmtv@gmail.com.\\n\\n\\n\\nTeotônio Vilela/AL, 25 de setembro de 2020.\\n\\n\\n\\nRICARDO LIMA TORRES\\nPregoeiro\\n\\n\\n\\nPublicado por:\\nEveraldo da Silva Oliveira Junior\\n\\nCódigo Identificador:DF593ED7\",\n  \"data_publicacao\": \"2020-09-28\"\n}"
]